Workbook
Name Category: 'Menu (Day 6 Ans)'!$C$2:$C$20
Name Category: OrderLines!$F$2:$F$925
Name ItemName: 'Menu (Day 6 Ans)'!$B$2:$B$20
Name OrderID: OrderLines!$A$2:$A$925
Name Qty: OrderLines!$C$2:$C$925
Name SKU: 'Menu (Day 6 Ans)'!$A$2:$A$20
Name SKU: OrderLines!$B$2:$B$925
Name Slicer_Branch1: #N/A
Name Slicer_Shift1: #N/A
Name SupplierID: 'Menu (Day 6 Ans)'!$D$2:$D$20
Name UnitCost: 'Menu (Day 6 Ans)'!$E$2:$E$20
Name UnitCost: OrderLines!$E$2:$E$925
Name UnitPrice: 'Menu (Day 6 Ans)'!$F$2:$F$20
Name UnitPrice: OrderLines!$D$2:$D$925

Sheet Orders
A1: OrderID | B1: OrderDateTime | C1: Branch | D1: CustomerType | E1: PaymentType | F1: Shift | G1: DiscountPct | H1: Revenue | I1: has beverage | J1: combo flag | K1: disc | L1: total cost | M1: profit | N1: Item list
A2: O00001 | B2: 45852.096 | C2: Head Office Café | D2: Visitor | E2: UPI | F2: Breakfast | G2: 0.06 | H2: =SUMIFS(OrderLines[LineNetAmount],OrderLines[OrderID],Orders[[#This Row],[OrderID]]) -> 147.909 | I2: =IF(COUNTIFS(OrderLines[OrderID],Orders[[#This Row],[OrderID]],OrderLines[Category],"Beverage"),"yes","no") -> no | J2: =IF(AND(COUNTIFS(OrderLines[OrderID],Orders[[#This Row],[OrderID]],OrderLines[Category],"Hot Meal"),Orders[[#This Row],[has beverage]]="yes"),"combo","single") -> single | K2: {=IF((SUMPRODUCT(OrderLines[UnitPrice],OrderLines[Qty],--(OrderLines[OrderID]=Orders[[#This Row],[OrderID]]))-Orders[[#This Row],[Revenue]])>40,"high disc","ok")} -> ok | L2: =SUMIFS(OrderLines[Food Cost],OrderLines[OrderID],Orders[[#This Row],[OrderID]]) -> 77.4 | M2: =Orders[[#This Row],[Revenue]]-Orders[[#This Row],[total cost]] -> 70.509 | N2: {=_xlfn.TEXTJOIN("+",,_xlfn._xlws.SORT(_xlfn.UNIQUE(_xlfn._xlws.FILTER(OrderLines[Category],OrderLines[OrderID]=Orders[[#This Row],[OrderID]]))))} -> Snack
A3: O00002 | B3: 45862.843 | C3: Plant 2 Canteen | D3: Staff | E3: Cash | F3: Dinner | G3: 0.05 | H3: =SUMIFS(OrderLines[LineNetAmount],OrderLines[OrderID],Orders[[#This Row],[OrderID]]) -> 101.5455 | I3: =IF(COUNTIFS(OrderLines[OrderID],Orders[[#This Row],[OrderID]],OrderLines[Category],"Beverage"),"yes","no") -> yes | J3: =IF(AND(COUNTIFS(OrderLines[OrderID],Orders[[#This Row],[OrderID]],OrderLines[Category],"Hot Meal"),Orders[[#This Row],[has beverage]]="yes"),"combo","single") -> single | K3: {=IF((SUMPRODUCT(OrderLines[UnitPrice],OrderLines[Qty],--(OrderLines[OrderID]=Orders[[#This Row],[OrderID]]))-Orders[[#This Row],[Revenue]])>40,"high disc","ok")} -> ok | L3: =SUMIFS(OrderLines[Food Cost],OrderLines[OrderID],Orders[[#This Row],[OrderID]]) -> 52.41 | M3: =Orders[[#This Row],[Revenue]]-Orders[[#This Row],[total cost]] -> 49.1355 | N3: {=_xlfn.TEXTJOIN("+",,_xlfn._xlws.SORT(_xlfn.UNIQUE(_xlfn._xlws.FILTER(OrderLines[Category],OrderLines[OrderID]=Orders[[#This Row],[OrderID]]))))} -> Beverage+Dessert
A4: O00003 | B4: 45848.661 | C4: Head Office Café | D4: Staff | E4: Card | F4: Lunch | G4: 0 | H4: =SUMIFS(OrderLines[LineNetAmount],OrderLines[OrderID],Orders[[#This Row],[OrderID]]) -> 668.96 | I4: =IF(COUNTIFS(OrderLines[OrderID],Orders[[#This Row],[OrderID]],OrderLines[Category],"Beverage"),"yes","no") -> yes | J4: =IF(AND(COUNTIFS(OrderLines[OrderID],Orders[[#This Row],[OrderID]],OrderLines[Category],"Hot Meal"),Orders[[#This Row],[has beverage]]="yes"),"combo","single") -> combo | K4: {=IF((SUMPRODUCT(OrderLines[UnitPrice],OrderLines[Qty],--(OrderLines[OrderID]=Orders[[#This Row],[OrderID]]))-Orders[[#This Row],[Revenue]])>40,"high disc","ok")} -> ok | L4: =SUMIFS(OrderLines[Food Cost],OrderLines[OrderID],Orders[[#This Row],[OrderID]]) -> 291.24 | M4: =Orders[[#This Row],[Revenue]]-Orders[[#This Row],[total cost]] -> 377.72 | N4: {=_xlfn.TEXTJOIN("+",,_xlfn._xlws.SORT(_xlfn.UNIQUE(_xlfn._xlws.FILTER(OrderLines[Category],OrderLines[OrderID]=Orders[[#This Row],[OrderID]]))))} -> Beverage+Hot Meal+Snack
A5: O00004 | B5: 45879.164 | C5: Plant 2 Canteen | D5: Visitor | E5: Cash | F5: Breakfast | G5: 0.03 | H5: =SUMIFS(OrderLines[LineNetAmount],OrderLines[OrderID],Orders[[#This Row],[OrderID]]) -> 477.4146 | I5: =IF(COUNTIFS(OrderLines[OrderID],Orders[[#This Row],[OrderID]],OrderLines[Category],"Beverage"),"yes","no") -> no | J5: =IF(AND(COUNTIFS(OrderLines[OrderID],Orders[[#This Row],[OrderID]],OrderLines[Category],"Hot Meal"),Orders[[#This Row],[has beverage]]="yes"),"combo","single") -> single | K5: {=IF((SUMPRODUCT(OrderLines[UnitPrice],OrderLines[Qty],--(OrderLines[OrderID]=Orders[[#This Row],[OrderID]]))-Orders[[#This Row],[Revenue]])>40,"high disc","ok")} -> ok | L5: =SUMIFS(OrderLines[Food Cost],OrderLines[OrderID],Orders[[#This Row],[OrderID]]) -> 224.16 | M5: =Orders[[#This Row],[Revenue]]-Orders[[#This Row],[total cost]] -> 253.2546 | N5: {=_xlfn.TEXTJOIN("+",,_xlfn._xlws.SORT(_xlfn.UNIQUE(_xlfn._xlws.FILTER(OrderLines[Category],OrderLines[OrderID]=Orders[[#This Row],[OrderID]]))))} -> Hot Meal
A6: O00005 | B6: 45845.135 | C6: Plant 2 Canteen | D6: Visitor | E6: Card | F6: Breakfast | G6: 0.04 | H6: =SUMIFS(OrderLines[LineNetAmount],OrderLines[OrderID],Orders[[#This Row],[OrderID]]) -> 95.0112 | I6: =IF(COUNTIFS(OrderLines[OrderID],Orders[[#This Row],[OrderID]],OrderLines[Category],"Beverage"),"yes","no") -> yes | J6: =IF(AND(COUNTIFS(OrderLines[OrderID],Orders[[#This Row],[OrderID]],OrderLines[Category],"Hot Meal"),Orders[[#This Row],[has beverage]]="yes"),"combo","single") -> single | K6: {=IF((SUMPRODUCT(OrderLines[UnitPrice],OrderLines[Qty],--(OrderLines[OrderID]=Orders[[#This Row],[OrderID]]))-Orders[[#This Row],[Revenue]])>40,"high disc","ok")} -> ok | L6: =SUMIFS(OrderLines[Food Cost],OrderLines[OrderID],Orders[[#This Row],[OrderID]]) -> 49.7 | M6: =Orders[[#This Row],[Revenue]]-Orders[[#This Row],[total cost]] -> 45.3112 | N6: {=_xlfn.TEXTJOIN("+",,_xlfn._xlws.SORT(_xlfn.UNIQUE(_xlfn._xlws.FILTER(OrderLines[Category],OrderLines[OrderID]=Orders[[#This Row],[OrderID]]))))} -> Beverage+Snack
A7: O00006 | B7: 45863.392 | C7: Plant 1 Canteen | D7: Worker | E7: UPI | F7: Breakfast | G7: 0.1 | H7: =SUMIFS(OrderLines[LineNetAmount],OrderLines[OrderID],Orders[[#This Row],[OrderID]]) -> 54.297 | I7: =IF(COUNTIFS(OrderLines[OrderID],Orders[[#This Row],[OrderID]],OrderLines[Category],"Beverage"),"yes","no") -> yes | J7: =IF(AND(COUNTIFS(OrderLines[OrderID],Orders[[#This Row],[OrderID]],OrderLines[Category],"Hot Meal"),Orders[[#This Row],[has beverage]]="yes"),"combo","single") -> single | K7: {=IF((SUMPRODUCT(OrderLines[UnitPrice],OrderLines[Qty],--(OrderLines[OrderID]=Orders[[#This Row],[OrderID]]))-Orders[[#This Row],[Revenue]])>40,"high disc","ok")} -> ok | L7: =SUMIFS(OrderLines[Food Cost],OrderLines[OrderID],Orders[[#This Row],[OrderID]]) -> 24 | M7: =Orders[[#This Row],[Revenue]]-Orders[[#This Row],[total cost]] -> 30.297 | N7: {=_xlfn.TEXTJOIN("+",,_xlfn._xlws.SORT(_xlfn.UNIQUE(_xlfn._xlws.FILTER(OrderLines[Category],OrderLines[OrderID]=Orders[[#This Row],[OrderID]]))))} -> Beverage
A8: O00007 | B8: 45852.86 | C8: Plant 2 Canteen | D8: Worker | E8: Card | F8: Dinner | G8: 0.07 | H8: =SUMIFS(OrderLines[LineNetAmount],OrderLines[OrderID],Orders[[#This Row],[OrderID]]) -> 348.4152 | I8: =IF(COUNTIFS(OrderLines[OrderID],Orders[[#This Row],[OrderID]],OrderLines[Category],"Beverage"),"yes","no") -> yes | J8: =IF(AND(COUNTIFS(OrderLines[OrderID],Orders[[#This Row],[OrderID]],OrderLines[Category],"Hot Meal"),Orders[[#This Row],[has beverage]]="yes"),"combo","single") -> combo | K8: {=IF((SUMPRODUCT(OrderLines[UnitPrice],OrderLines[Qty],--(OrderLines[OrderID]=Orders[[#This Row],[OrderID]]))-Orders[[#This Row],[Revenue]])>40,"high disc","ok")} -> ok | L8: =SUMIFS(OrderLines[Food Cost],OrderLines[OrderID],Orders[[#This Row],[OrderID]]) -> 159.98 | M8: =Orders[[#This Row],[Revenue]]-Orders[[#This Row],[total cost]] -> 188.4352 | N8: {=_xlfn.TEXTJOIN("+",,_xlfn._xlws.SORT(_xlfn.UNIQUE(_xlfn._xlws.FILTER(OrderLines[Category],OrderLines[OrderID]=Orders[[#This Row],[OrderID]]))))} -> Beverage+Hot Meal
A9: O00008 | B9: 45863.504 | C9: Plant 1 Canteen | D9: Staff | E9: UPI | F9: Lunch | G9: 0 | H9: =SUMIFS(OrderLines[LineNetAmount],OrderLines[OrderID],Orders[[#This Row],[OrderID]]) -> 223.75 | I9: =IF(COUNTIFS(OrderLines[OrderID],Orders[[#This Row],[OrderID]],OrderLines[Category],"Beverage"),"yes","no") -> yes | J9: =IF(AND(COUNTIFS(OrderLines[OrderID],Orders[[#This Row],[OrderID]],OrderLines[Category],"Hot Meal"),Orders[[#This Row],[has beverage]]="yes"),"combo","single") -> single | K9: {=IF((SUMPRODUCT(OrderLines[UnitPrice],OrderLines[Qty],--(OrderLines[OrderID]=Orders[[#This Row],[OrderID]]))-Orders[[#This Row],[Revenue]])>40,"high disc","ok")} -> ok | L9: =SUMIFS(OrderLines[Food Cost],OrderLines[OrderID],Orders[[#This Row],[OrderID]]) -> 110.98 | M9: =Orders[[#This Row],[Revenue]]-Orders[[#This Row],[total cost]] -> 112.77 | N9: {=_xlfn.TEXTJOIN("+",,_xlfn._xlws.SORT(_xlfn.UNIQUE(_xlfn._xlws.FILTER(OrderLines[Category],OrderLines[OrderID]=Orders[[#This Row],[OrderID]]))))} -> Beverage+Dessert
A10: O00009 | B10: 45844.162 | C10: Head Office Café | D10: Visitor | E10: Cash | F10: Breakfast | G10: 0.07 | H10: =SUMIFS(OrderLines[LineNetAmount],OrderLines[OrderID],Orders[[#This Row],[OrderID]]) -> 459.2898 | I10: =IF(COUNTIFS(OrderLines[OrderID],Orders[[#This Row],[OrderID]],OrderLines[Category],"Beverage"),"yes","no") -> no | J10: =IF(AND(COUNTIFS(OrderLines[OrderID],Orders[[#This Row],[OrderID]],OrderLines[Category],"Hot Meal"),Orders[[#This Row],[has beverage]]="yes"),"combo","single") -> single | K10: {=IF((SUMPRODUCT(OrderLines[UnitPrice],OrderLines[Qty],--(OrderLines[OrderID]=Orders[[#This Row],[OrderID]]))-Orders[[#This Row],[Revenue]])>40,"high disc","ok")} -> ok | L10: =SUMIFS(OrderLines[Food Cost],OrderLines[OrderID],Orders[[#This Row],[OrderID]]) -> 225.97 | M10: =Orders[[#This Row],[Revenue]]-Orders[[#This Row],[total cost]] -> 233.3198 | N10: {=_xlfn.TEXTJOIN("+",,_xlfn._xlws.SORT(_xlfn.UNIQUE(_xlfn._xlws.FILTER(OrderLines[Category],OrderLines[OrderID]=Orders[[#This Row],[OrderID]]))))} -> Dessert+Hot Meal+Snack
A11: O00010 | B11: 45862.2 | C11: Plant 1 Canteen | D11: Staff | E11: Card | F11: Breakfast | G11: 0.04 | H11: =SUMIFS(OrderLines[LineNetAmount],OrderLines[OrderID],Orders[[#This Row],[OrderID]]) -> 420.0768 | I11: =IF(COUNTIFS(OrderLines[OrderID],Orders[[#This Row],[OrderID]],OrderLines[Category],"Beverage"),"yes","no") -> yes | J11: =IF(AND(COUNTIFS(OrderLines[OrderID],Orders[[#This Row],[OrderID]],OrderLines[Category],"Hot Meal"),Orders[[#This Row],[has beverage]]="yes"),"combo","single") -> combo | K11: {=IF((SUMPRODUCT(OrderLines[UnitPrice],OrderLines[Qty],--(OrderLines[OrderID]=Orders[[#This Row],[OrderID]]))-Orders[[#This Row],[Revenue]])>40,"high disc","ok")} -> ok | L11: =SUMIFS(OrderLines[Food Cost],OrderLines[OrderID],Orders[[#This Row],[OrderID]]) -> 204.88 | M11: =Orders[[#This Row],[Revenue]]-Orders[[#This Row],[total cost]] -> 215.1968 | N11: {=_xlfn.TEXTJOIN("+",,_xlfn._xlws.SORT(_xlfn.UNIQUE(_xlfn._xlws.FILTER(OrderLines[Category],OrderLines[OrderID]=Orders[[#This Row],[OrderID]]))))} -> Beverage+Dessert+Hot Meal+Snack
A12: O00011 | B12: 45860.003 | C12: Plant 2 Canteen | D12: Worker | E12: Cash | F12: Breakfast | G12: 0.03 | H12: =SUMIFS(OrderLines[LineNetAmount],OrderLines[OrderID],Orders[[#This Row],[OrderID]]) -> 27.5771 | I12: =IF(COUNTIFS(OrderLines[OrderID],Orders[[#This Row],[OrderID]],OrderLines[Category],"Beverage"),"yes","no") -> yes | J12: =IF(AND(COUNTIFS(OrderLines[OrderID],Orders[[#This Row],[OrderID]],OrderLines[Category],"Hot Meal"),Orders[[#This Row],[has beverage]]="yes"),"combo","single") -> single | K12: {=IF((SUMPRODUCT(OrderLines[UnitPrice],OrderLines[Qty],--(OrderLines[OrderID]=Orders[[#This Row],[OrderID]]))-Orders[[#This Row],[Revenue]])>40,"high disc","ok")} -> ok | L12: =SUMIFS(OrderLines[Food Cost],OrderLines[OrderID],Orders[[#This Row],[OrderID]]) -> 13.89 | M12: =Orders[[#This Row],[Revenue]]-Orders[[#This Row],[total cost]] -> 13.6871 | N12: {=_xlfn.TEXTJOIN("+",,_xlfn._xlws.SORT(_xlfn.UNIQUE(_xlfn._xlws.FILTER(OrderLines[Category],OrderLines[OrderID]=Orders[[#This Row],[OrderID]]))))} -> Beverage
A13: O00012 | B13: 45839.459 | C13: Plant 2 Canteen | D13: Staff | E13: Card | F13: Lunch | G13: 0.08 | H13: =SUMIFS(OrderLines[LineNetAmount],OrderLines[OrderID],Orders[[#This Row],[OrderID]]) -> 98.118 | I13: =IF(COUNTIFS(OrderLines[OrderID],Orders[[#This Row],[OrderID]],OrderLines[Category],"Beverage"),"yes","no") -> no | J13: =IF(AND(COUNTIFS(OrderLines[OrderID],Orders[[#This Row],[OrderID]],OrderLines[Category],"Hot Meal"),Orders[[#This Row],[has beverage]]="yes"),"combo","single") -> single | K13: {=IF((SUMPRODUCT(OrderLines[UnitPrice],OrderLines[Qty],--(OrderLines[OrderID]=Orders[[#This Row],[OrderID]]))-Orders[[#This Row],[Revenue]])>40,"high disc","ok")} -> ok | L13: =SUMIFS(OrderLines[Food Cost],OrderLines[OrderID],Orders[[#This Row],[OrderID]]) -> 47.75 | M13: =Orders[[#This Row],[Revenue]]-Orders[[#This Row],[total cost]] -> 50.368 | N13: {=_xlfn.TEXTJOIN("+",,_xlfn._xlws.SORT(_xlfn.UNIQUE(_xlfn._xlws.FILTER(OrderLines[Category],OrderLines[OrderID]=Orders[[#This Row],[OrderID]]))))} -> Dessert+Snack
... A361: O00360 | B361: 45878.689 | C361: Plant 2 Canteen | D361: Visitor | E361: UPI | F361: Dinner | G361: 0.04 | H361: =SUMIFS(OrderLines[LineNetAmount],OrderLines[OrderID],Orders[[#This Row],[OrderID]]) -> 962.1504 | I361: =IF(COUNTIFS(OrderLines[OrderID],Orders[[#This Row],[OrderID]],OrderLines[Category],"Beverage"),"yes","no") -> yes | J361: =IF(AND(COUNTIFS(OrderLines[OrderID],Orders[[#This Row],[OrderID]],OrderLines[Category],"Hot Meal"),Orders[[#This Row],[has beverage]]="yes"),"combo","single") -> combo | K361: {=IF((SUMPRODUCT(OrderLines[UnitPrice],OrderLines[Qty],--(OrderLines[OrderID]=Orders[[#This Row],[OrderID]]))-Orders[[#This Row],[Revenue]])>40,"high disc","ok")} -> high disc | L361: =SUMIFS(OrderLines[Food Cost],OrderLines[OrderID],Orders[[#This Row],[OrderID]]) -> 466.15 | M361: =Orders[[#This Row],[Revenue]]-Orders[[#This Row],[total cost]] -> 496.0004 | N361: {=_xlfn.TEXTJOIN("+",,_xlfn._xlws.SORT(_xlfn.UNIQUE(_xlfn._xlws.FILTER(OrderLines[Category],OrderLines[OrderID]=Orders[[#This Row],[OrderID]]))))} -> Beverage+Hot Meal

Sheet OrderLines
A1: OrderID | B1: SKU | C1: Qty | D1: UnitPrice | E1: UnitCost | F1: Category | G1: Item category | H1: OrderDateTime | I1: Branch | J1: DiscountPct | K1: PaymentType | L1: Shift | M1: LineNetAmount | N1: Combo Flag | O1: DiscountFlag | P1: Food Cost | Q1: Gross Profit
A2: O00001 | B2: SHJ7XV | C2: 3 | D2: {=VLOOKUP(OrderLines[[#This Row],[SKU]:[SKU]],Menu[],MATCH(OrderLines[[#Headers],[UnitPrice]],Menu[#Headers],0),FALSE)} -> 52.45 | E2: {=VLOOKUP(OrderLines[[#This Row],[SKU]:[SKU]],Menu[],MATCH(OrderLines[[#Headers],[UnitCost]],Menu[#Headers],0),FALSE)} -> 25.8 | F2: {=VLOOKUP(OrderLines[[#This Row],[SKU]:[SKU]],Menu[],MATCH(OrderLines[[#Headers],[Category]],Menu[#Headers],0),FALSE)} -> Snack | G2: {=_xlfn.TEXTJOIN("+",TRUE,_xlfn._xlws.SORT(_xlfn.UNIQUE(_xlfn._xlws.FILTER(OrderLines[Category],OrderLines[OrderID]=OrderLines[[#This Row],[OrderID]]))))} -> Snack | H2: {=INT(VLOOKUP(OrderLines[[#This Row],[OrderID]:[OrderID]],Orders[],MATCH(OrderLines[[#Headers],[OrderDateTime]],Orders[#Headers],0),FALSE))} -> 45852 | I2: {=VLOOKUP(OrderLines[[#This Row],[OrderID]:[OrderID]],Orders[],MATCH(OrderLines[[#Headers],[Branch]],Orders[#Headers],0),FALSE)} -> Head Office Café | J2: {=VLOOKUP(OrderLines[[#This Row],[OrderID]:[OrderID]],Orders[],MATCH(OrderLines[[#Headers],[DiscountPct]],Orders[#Headers],0),FALSE)} -> 0.06 | K2: {=VLOOKUP(OrderLines[[#This Row],[OrderID]:[OrderID]],Orders[],MATCH(OrderLines[[#Headers],[PaymentType]],Orders[#Headers],0),FALSE)} -> UPI | L2: {=VLOOKUP(OrderLines[[#This Row],[OrderID]:[OrderID]],Orders[],MATCH(OrderLines[[#Headers],[Shift]],Orders[#Headers],0),FALSE)} -> Breakfast | M2: =(OrderLines[[#This Row],[Qty]]*OrderLines[[#This Row],[UnitPrice]])*(1-OrderLines[[#This Row],[DiscountPct]]) -> 147.909 | N2: =IF(AND(COUNTIFS(OrderLines[OrderID],OrderLines[[#This Row],[OrderID]],OrderLines[Category],"Hot Meal"),COUNTIFS(OrderLines[OrderID],OrderLines[[#This Row],[OrderID]],OrderLines[Category],"Beverage")),"Combo","Single") -> Single | O2: {=IF(SUMPRODUCT(OrderLines[UnitPrice],OrderLines[Qty],OrderLines[DiscountPct],--(OrderLines[OrderID] = OrderLines[[#This Row],[OrderID]]))>40,"High Discount","Ok")} -> Ok | P2: =OrderLines[[#This Row],[UnitCost]]*OrderLines[[#This Row],[Qty]] -> 77.4 | Q2: =OrderLines[[#This Row],[LineNetAmount]]-OrderLines[[#This Row],[Food Cost]] -> 70.509
A3: O00002 | B3: BTIQJ7 | C3: 1 | D3: {=VLOOKUP(OrderLines[[#This Row],[SKU]:[SKU]],Menu[],MATCH(OrderLines[[#Headers],[UnitPrice]],Menu[#Headers],0),FALSE)} -> 30.34 | E3: {=VLOOKUP(OrderLines[[#This Row],[SKU]:[SKU]],Menu[],MATCH(OrderLines[[#Headers],[UnitCost]],Menu[#Headers],0),FALSE)} -> 14.18 | F3: {=VLOOKUP(OrderLines[[#This Row],[SKU]:[SKU]],Menu[],MATCH(OrderLines[[#Headers],[Category]],Menu[#Headers],0),FALSE)} -> Beverage | G3: {=_xlfn.TEXTJOIN("+",TRUE,_xlfn._xlws.SORT(_xlfn.UNIQUE(_xlfn._xlws.FILTER(OrderLines[Category],OrderLines[OrderID]=OrderLines[[#This Row],[OrderID]]))))} -> Beverage+Dessert | H3: {=INT(VLOOKUP(OrderLines[[#This Row],[OrderID]:[OrderID]],Orders[],MATCH(OrderLines[[#Headers],[OrderDateTime]],Orders[#Headers],0),FALSE))} -> 45862 | I3: {=VLOOKUP(OrderLines[[#This Row],[OrderID]:[OrderID]],Orders[],MATCH(OrderLines[[#Headers],[Branch]],Orders[#Headers],0),FALSE)} -> Plant 2 Canteen | J3: {=VLOOKUP(OrderLines[[#This Row],[OrderID]:[OrderID]],Orders[],MATCH(OrderLines[[#Headers],[DiscountPct]],Orders[#Headers],0),FALSE)} -> 0.05 | K3: {=VLOOKUP(OrderLines[[#This Row],[OrderID]:[OrderID]],Orders[],MATCH(OrderLines[[#Headers],[PaymentType]],Orders[#Headers],0),FALSE)} -> Cash | L3: {=VLOOKUP(OrderLines[[#This Row],[OrderID]:[OrderID]],Orders[],MATCH(OrderLines[[#Headers],[Shift]],Orders[#Headers],0),FALSE)} -> Dinner | M3: =(OrderLines[[#This Row],[Qty]]*OrderLines[[#This Row],[UnitPrice]])*(1-OrderLines[[#This Row],[DiscountPct]]) -> 28.823 | N3: =IF(AND(COUNTIFS(OrderLines[OrderID],OrderLines[[#This Row],[OrderID]],OrderLines[Category],"Hot Meal"),COUNTIFS(OrderLines[OrderID],OrderLines[[#This Row],[OrderID]],OrderLines[Category],"Beverage")),"Combo","Single") -> Single | O3: {=IF(SUMPRODUCT(OrderLines[UnitPrice],OrderLines[Qty],OrderLines[DiscountPct],--(OrderLines[OrderID] = OrderLines[[#This Row],[OrderID]]))>40,"High Discount","Ok")} -> Ok | P3: =OrderLines[[#This Row],[UnitCost]]*OrderLines[[#This Row],[Qty]] -> 14.18 | Q3: =OrderLines[[#This Row],[LineNetAmount]]-OrderLines[[#This Row],[Food Cost]] -> 14.643
A4: O00002 | B4: DH9SDB | C4: 1 | D4: {=VLOOKUP(OrderLines[[#This Row],[SKU]:[SKU]],Menu[],MATCH(OrderLines[[#Headers],[UnitPrice]],Menu[#Headers],0),FALSE)} -> 76.55 | E4: {=VLOOKUP(OrderLines[[#This Row],[SKU]:[SKU]],Menu[],MATCH(OrderLines[[#Headers],[UnitCost]],Menu[#Headers],0),FALSE)} -> 38.23 | F4: {=VLOOKUP(OrderLines[[#This Row],[SKU]:[SKU]],Menu[],MATCH(OrderLines[[#Headers],[Category]],Menu[#Headers],0),FALSE)} -> Dessert | G4: {=_xlfn.TEXTJOIN("+",TRUE,_xlfn._xlws.SORT(_xlfn.UNIQUE(_xlfn._xlws.FILTER(OrderLines[Category],OrderLines[OrderID]=OrderLines[[#This Row],[OrderID]]))))} -> Beverage+Dessert | H4: {=INT(VLOOKUP(OrderLines[[#This Row],[OrderID]:[OrderID]],Orders[],MATCH(OrderLines[[#Headers],[OrderDateTime]],Orders[#Headers],0),FALSE))} -> 45862 | I4: {=VLOOKUP(OrderLines[[#This Row],[OrderID]:[OrderID]],Orders[],MATCH(OrderLines[[#Headers],[Branch]],Orders[#Headers],0),FALSE)} -> Plant 2 Canteen | J4: {=VLOOKUP(OrderLines[[#This Row],[OrderID]:[OrderID]],Orders[],MATCH(OrderLines[[#Headers],[DiscountPct]],Orders[#Headers],0),FALSE)} -> 0.05 | K4: {=VLOOKUP(OrderLines[[#This Row],[OrderID]:[OrderID]],Orders[],MATCH(OrderLines[[#Headers],[PaymentType]],Orders[#Headers],0),FALSE)} -> Cash | L4: {=VLOOKUP(OrderLines[[#This Row],[OrderID]:[OrderID]],Orders[],MATCH(OrderLines[[#Headers],[Shift]],Orders[#Headers],0),FALSE)} -> Dinner | M4: =(OrderLines[[#This Row],[Qty]]*OrderLines[[#This Row],[UnitPrice]])*(1-OrderLines[[#This Row],[DiscountPct]]) -> 72.7225 | N4: =IF(AND(COUNTIFS(OrderLines[OrderID],OrderLines[[#This Row],[OrderID]],OrderLines[Category],"Hot Meal"),COUNTIFS(OrderLines[OrderID],OrderLines[[#This Row],[OrderID]],OrderLines[Category],"Beverage")),"Combo","Single") -> Single | O4: {=IF(SUMPRODUCT(OrderLines[UnitPrice],OrderLines[Qty],OrderLines[DiscountPct],--(OrderLines[OrderID] = OrderLines[[#This Row],[OrderID]]))>40,"High Discount","Ok")} -> Ok | P4: =OrderLines[[#This Row],[UnitCost]]*OrderLines[[#This Row],[Qty]] -> 38.23 | Q4: =OrderLines[[#This Row],[LineNetAmount]]-OrderLines[[#This Row],[Food Cost]] -> 34.4925
A5: O00003 | B5: BOC6UZ | C5: 2 | D5: {=VLOOKUP(OrderLines[[#This Row],[SKU]:[SKU]],Menu[],MATCH(OrderLines[[#Headers],[UnitPrice]],Menu[#Headers],0),FALSE)} -> 32.98 | E5: {=VLOOKUP(OrderLines[[#This Row],[SKU]:[SKU]],Menu[],MATCH(OrderLines[[#Headers],[UnitCost]],Menu[#Headers],0),FALSE)} -> 11.84 | F5: {=VLOOKUP(OrderLines[[#This Row],[SKU]:[SKU]],Menu[],MATCH(OrderLines[[#Headers],[Category]],Menu[#Headers],0),FALSE)} -> Beverage | G5: {=_xlfn.TEXTJOIN("+",TRUE,_xlfn._xlws.SORT(_xlfn.UNIQUE(_xlfn._xlws.FILTER(OrderLines[Category],OrderLines[OrderID]=OrderLines[[#This Row],[OrderID]]))))} -> Beverage+Hot Meal+Snack | H5: {=INT(VLOOKUP(OrderLines[[#This Row],[OrderID]:[OrderID]],Orders[],MATCH(OrderLines[[#Headers],[OrderDateTime]],Orders[#Headers],0),FALSE))} -> 45848 | I5: {=VLOOKUP(OrderLines[[#This Row],[OrderID]:[OrderID]],Orders[],MATCH(OrderLines[[#Headers],[Branch]],Orders[#Headers],0),FALSE)} -> Head Office Café | J5: {=VLOOKUP(OrderLines[[#This Row],[OrderID]:[OrderID]],Orders[],MATCH(OrderLines[[#Headers],[DiscountPct]],Orders[#Headers],0),FALSE)} -> 0 | K5: {=VLOOKUP(OrderLines[[#This Row],[OrderID]:[OrderID]],Orders[],MATCH(OrderLines[[#Headers],[PaymentType]],Orders[#Headers],0),FALSE)} -> Card | L5: {=VLOOKUP(OrderLines[[#This Row],[OrderID]:[OrderID]],Orders[],MATCH(OrderLines[[#Headers],[Shift]],Orders[#Headers],0),FALSE)} -> Lunch | M5: =(OrderLines[[#This Row],[Qty]]*OrderLines[[#This Row],[UnitPrice]])*(1-OrderLines[[#This Row],[DiscountPct]]) -> 65.96 | N5: =IF(AND(COUNTIFS(OrderLines[OrderID],OrderLines[[#This Row],[OrderID]],OrderLines[Category],"Hot Meal"),COUNTIFS(OrderLines[OrderID],OrderLines[[#This Row],[OrderID]],OrderLines[Category],"Beverage")),"Combo","Single") -> Combo | O5: {=IF(SUMPRODUCT(OrderLines[UnitPrice],OrderLines[Qty],OrderLines[DiscountPct],--(OrderLines[OrderID] = OrderLines[[#This Row],[OrderID]]))>40,"High Discount","Ok")} -> Ok | P5: =OrderLines[[#This Row],[UnitCost]]*OrderLines[[#This Row],[Qty]] -> 23.68 | Q5: =OrderLines[[#This Row],[LineNetAmount]]-OrderLines[[#This Row],[Food Cost]] -> 42.28
A6: O00003 | B6: SHJ7XV | C6: 1 | D6: {=VLOOKUP(OrderLines[[#This Row],[SKU]:[SKU]],Menu[],MATCH(OrderLines[[#Headers],[UnitPrice]],Menu[#Headers],0),FALSE)} -> 52.45 | E6: {=VLOOKUP(OrderLines[[#This Row],[SKU]:[SKU]],Menu[],MATCH(OrderLines[[#Headers],[UnitCost]],Menu[#Headers],0),FALSE)} -> 25.8 | F6: {=VLOOKUP(OrderLines[[#This Row],[SKU]:[SKU]],Menu[],MATCH(OrderLines[[#Headers],[Category]],Menu[#Headers],0),FALSE)} -> Snack | G6: {=_xlfn.TEXTJOIN("+",TRUE,_xlfn._xlws.SORT(_xlfn.UNIQUE(_xlfn._xlws.FILTER(OrderLines[Category],OrderLines[OrderID]=OrderLines[[#This Row],[OrderID]]))))} -> Beverage+Hot Meal+Snack | H6: {=INT(VLOOKUP(OrderLines[[#This Row],[OrderID]:[OrderID]],Orders[],MATCH(OrderLines[[#Headers],[OrderDateTime]],Orders[#Headers],0),FALSE))} -> 45848 | I6: {=VLOOKUP(OrderLines[[#This Row],[OrderID]:[OrderID]],Orders[],MATCH(OrderLines[[#Headers],[Branch]],Orders[#Headers],0),FALSE)} -> Head Office Café | J6: {=VLOOKUP(OrderLines[[#This Row],[OrderID]:[OrderID]],Orders[],MATCH(OrderLines[[#Headers],[DiscountPct]],Orders[#Headers],0),FALSE)} -> 0 | K6: {=VLOOKUP(OrderLines[[#This Row],[OrderID]:[OrderID]],Orders[],MATCH(OrderLines[[#Headers],[PaymentType]],Orders[#Headers],0),FALSE)} -> Card | L6: {=VLOOKUP(OrderLines[[#This Row],[OrderID]:[OrderID]],Orders[],MATCH(OrderLines[[#Headers],[Shift]],Orders[#Headers],0),FALSE)} -> Lunch | M6: =(OrderLines[[#This Row],[Qty]]*OrderLines[[#This Row],[UnitPrice]])*(1-OrderLines[[#This Row],[DiscountPct]]) -> 52.45 | N6: =IF(AND(COUNTIFS(OrderLines[OrderID],OrderLines[[#This Row],[OrderID]],OrderLines[Category],"Hot Meal"),COUNTIFS(OrderLines[OrderID],OrderLines[[#This Row],[OrderID]],OrderLines[Category],"Beverage")),"Combo","Single") -> Combo | O6: {=IF(SUMPRODUCT(OrderLines[UnitPrice],OrderLines[Qty],OrderLines[DiscountPct],--(OrderLines[OrderID] = OrderLines[[#This Row],[OrderID]]))>40,"High Discount","Ok")} -> Ok | P6: =OrderLines[[#This Row],[UnitCost]]*OrderLines[[#This Row],[Qty]] -> 25.8 | Q6: =OrderLines[[#This Row],[LineNetAmount]]-OrderLines[[#This Row],[Food Cost]] -> 26.65
A7: O00003 | B7: H3A3ZM | C7: 3 | D7: {=VLOOKUP(OrderLines[[#This Row],[SKU]:[SKU]],Menu[],MATCH(OrderLines[[#Headers],[UnitPrice]],Menu[#Headers],0),FALSE)} -> 170.83 | E7: {=VLOOKUP(OrderLines[[#This Row],[SKU]:[SKU]],Menu[],MATCH(OrderLines[[#Headers],[UnitCost]],Menu[#Headers],0),FALSE)} -> 74.07 | F7: {=VLOOKUP(OrderLines[[#This Row],[SKU]:[SKU]],Menu[],MATCH(OrderLines[[#Headers],[Category]],Menu[#Headers],0),FALSE)} -> Hot Meal | G7: {=_xlfn.TEXTJOIN("+",TRUE,_xlfn._xlws.SORT(_xlfn.UNIQUE(_xlfn._xlws.FILTER(OrderLines[Category],OrderLines[OrderID]=OrderLines[[#This Row],[OrderID]]))))} -> Beverage+Hot Meal+Snack | H7: {=INT(VLOOKUP(OrderLines[[#This Row],[OrderID]:[OrderID]],Orders[],MATCH(OrderLines[[#Headers],[OrderDateTime]],Orders[#Headers],0),FALSE))} -> 45848 | I7: {=VLOOKUP(OrderLines[[#This Row],[OrderID]:[OrderID]],Orders[],MATCH(OrderLines[[#Headers],[Branch]],Orders[#Headers],0),FALSE)} -> Head Office Café | J7: {=VLOOKUP(OrderLines[[#This Row],[OrderID]:[OrderID]],Orders[],MATCH(OrderLines[[#Headers],[DiscountPct]],Orders[#Headers],0),FALSE)} -> 0 | K7: {=VLOOKUP(OrderLines[[#This Row],[OrderID]:[OrderID]],Orders[],MATCH(OrderLines[[#Headers],[PaymentType]],Orders[#Headers],0),FALSE)} -> Card | L7: {=VLOOKUP(OrderLines[[#This Row],[OrderID]:[OrderID]],Orders[],MATCH(OrderLines[[#Headers],[Shift]],Orders[#Headers],0),FALSE)} -> Lunch | M7: =(OrderLines[[#This Row],[Qty]]*OrderLines[[#This Row],[UnitPrice]])*(1-OrderLines[[#This Row],[DiscountPct]]) -> 512.49 | N7: =IF(AND(COUNTIFS(OrderLines[OrderID],OrderLines[[#This Row],[OrderID]],OrderLines[Category],"Hot Meal"),COUNTIFS(OrderLines[OrderID],OrderLines[[#This Row],[OrderID]],OrderLines[Category],"Beverage")),"Combo","Single") -> Combo | O7: {=IF(SUMPRODUCT(OrderLines[UnitPrice],OrderLines[Qty],OrderLines[DiscountPct],--(OrderLines[OrderID] = OrderLines[[#This Row],[OrderID]]))>40,"High Discount","Ok")} -> Ok | P7: =OrderLines[[#This Row],[UnitCost]]*OrderLines[[#This Row],[Qty]] -> 222.21 | Q7: =OrderLines[[#This Row],[LineNetAmount]]-OrderLines[[#This Row],[Food Cost]] -> 290.28
A8: O00003 | B8: SZBIKC | C8: 1 | D8: {=VLOOKUP(OrderLines[[#This Row],[SKU]:[SKU]],Menu[],MATCH(OrderLines[[#Headers],[UnitPrice]],Menu[#Headers],0),FALSE)} -> 38.06 | E8: {=VLOOKUP(OrderLines[[#This Row],[SKU]:[SKU]],Menu[],MATCH(OrderLines[[#Headers],[UnitCost]],Menu[#Headers],0),FALSE)} -> 19.55 | F8: {=VLOOKUP(OrderLines[[#This Row],[SKU]:[SKU]],Menu[],MATCH(OrderLines[[#Headers],[Category]],Menu[#Headers],0),FALSE)} -> Snack | G8: {=_xlfn.TEXTJOIN("+",TRUE,_xlfn._xlws.SORT(_xlfn.UNIQUE(_xlfn._xlws.FILTER(OrderLines[Category],OrderLines[OrderID]=OrderLines[[#This Row],[OrderID]]))))} -> Beverage+Hot Meal+Snack | H8: {=INT(VLOOKUP(OrderLines[[#This Row],[OrderID]:[OrderID]],Orders[],MATCH(OrderLines[[#Headers],[OrderDateTime]],Orders[#Headers],0),FALSE))} -> 45848 | I8: {=VLOOKUP(OrderLines[[#This Row],[OrderID]:[OrderID]],Orders[],MATCH(OrderLines[[#Headers],[Branch]],Orders[#Headers],0),FALSE)} -> Head Office Café | J8: {=VLOOKUP(OrderLines[[#This Row],[OrderID]:[OrderID]],Orders[],MATCH(OrderLines[[#Headers],[DiscountPct]],Orders[#Headers],0),FALSE)} -> 0 | K8: {=VLOOKUP(OrderLines[[#This Row],[OrderID]:[OrderID]],Orders[],MATCH(OrderLines[[#Headers],[PaymentType]],Orders[#Headers],0),FALSE)} -> Card | L8: {=VLOOKUP(OrderLines[[#This Row],[OrderID]:[OrderID]],Orders[],MATCH(OrderLines[[#Headers],[Shift]],Orders[#Headers],0),FALSE)} -> Lunch | M8: =(OrderLines[[#This Row],[Qty]]*OrderLines[[#This Row],[UnitPrice]])*(1-OrderLines[[#This Row],[DiscountPct]]) -> 38.06 | N8: =IF(AND(COUNTIFS(OrderLines[OrderID],OrderLines[[#This Row],[OrderID]],OrderLines[Category],"Hot Meal"),COUNTIFS(OrderLines[OrderID],OrderLines[[#This Row],[OrderID]],OrderLines[Category],"Beverage")),"Combo","Single") -> Combo | O8: {=IF(SUMPRODUCT(OrderLines[UnitPrice],OrderLines[Qty],OrderLines[DiscountPct],--(OrderLines[OrderID] = OrderLines[[#This Row],[OrderID]]))>40,"High Discount","Ok")} -> Ok | P8: =OrderLines[[#This Row],[UnitCost]]*OrderLines[[#This Row],[Qty]] -> 19.55 | Q8: =OrderLines[[#This Row],[LineNetAmount]]-OrderLines[[#This Row],[Food Cost]] -> 18.51
A9: O00004 | B9: HH1DNM | C9: 2 | D9: {=VLOOKUP(OrderLines[[#This Row],[SKU]:[SKU]],Menu[],MATCH(OrderLines[[#Headers],[UnitPrice]],Menu[#Headers],0),FALSE)} -> 246.09 | E9: {=VLOOKUP(OrderLines[[#This Row],[SKU]:[SKU]],Menu[],MATCH(OrderLines[[#Headers],[UnitCost]],Menu[#Headers],0),FALSE)} -> 112.08 | F9: {=VLOOKUP(OrderLines[[#This Row],[SKU]:[SKU]],Menu[],MATCH(OrderLines[[#Headers],[Category]],Menu[#Headers],0),FALSE)} -> Hot Meal | G9: {=_xlfn.TEXTJOIN("+",TRUE,_xlfn._xlws.SORT(_xlfn.UNIQUE(_xlfn._xlws.FILTER(OrderLines[Category],OrderLines[OrderID]=OrderLines[[#This Row],[OrderID]]))))} -> Hot Meal | H9: {=INT(VLOOKUP(OrderLines[[#This Row],[OrderID]:[OrderID]],Orders[],MATCH(OrderLines[[#Headers],[OrderDateTime]],Orders[#Headers],0),FALSE))} -> 45879 | I9: {=VLOOKUP(OrderLines[[#This Row],[OrderID]:[OrderID]],Orders[],MATCH(OrderLines[[#Headers],[Branch]],Orders[#Headers],0),FALSE)} -> Plant 2 Canteen | J9: {=VLOOKUP(OrderLines[[#This Row],[OrderID]:[OrderID]],Orders[],MATCH(OrderLines[[#Headers],[DiscountPct]],Orders[#Headers],0),FALSE)} -> 0.03 | K9: {=VLOOKUP(OrderLines[[#This Row],[OrderID]:[OrderID]],Orders[],MATCH(OrderLines[[#Headers],[PaymentType]],Orders[#Headers],0),FALSE)} -> Cash | L9: {=VLOOKUP(OrderLines[[#This Row],[OrderID]:[OrderID]],Orders[],MATCH(OrderLines[[#Headers],[Shift]],Orders[#Headers],0),FALSE)} -> Breakfast | M9: =(OrderLines[[#This Row],[Qty]]*OrderLines[[#This Row],[UnitPrice]])*(1-OrderLines[[#This Row],[DiscountPct]]) -> 477.4146 | N9: =IF(AND(COUNTIFS(OrderLines[OrderID],OrderLines[[#This Row],[OrderID]],OrderLines[Category],"Hot Meal"),COUNTIFS(OrderLines[OrderID],OrderLines[[#This Row],[OrderID]],OrderLines[Category],"Beverage")),"Combo","Single") -> Single | O9: {=IF(SUMPRODUCT(OrderLines[UnitPrice],OrderLines[Qty],OrderLines[DiscountPct],--(OrderLines[OrderID] = OrderLines[[#This Row],[OrderID]]))>40,"High Discount","Ok")} -> Ok | P9: =OrderLines[[#This Row],[UnitCost]]*OrderLines[[#This Row],[Qty]] -> 224.16 | Q9: =OrderLines[[#This Row],[LineNetAmount]]-OrderLines[[#This Row],[Food Cost]] -> 253.2546
A10: O00005 | B10: SCKW5N | C10: 1 | D10: {=VLOOKUP(OrderLines[[#This Row],[SKU]:[SKU]],Menu[],MATCH(OrderLines[[#Headers],[UnitPrice]],Menu[#Headers],0),FALSE)} -> 70.54 | E10: {=VLOOKUP(OrderLines[[#This Row],[SKU]:[SKU]],Menu[],MATCH(OrderLines[[#Headers],[UnitCost]],Menu[#Headers],0),FALSE)} -> 35.81 | F10: {=VLOOKUP(OrderLines[[#This Row],[SKU]:[SKU]],Menu[],MATCH(OrderLines[[#Headers],[Category]],Menu[#Headers],0),FALSE)} -> Snack | G10: {=_xlfn.TEXTJOIN("+",TRUE,_xlfn._xlws.SORT(_xlfn.UNIQUE(_xlfn._xlws.FILTER(OrderLines[Category],OrderLines[OrderID]=OrderLines[[#This Row],[OrderID]]))))} -> Beverage+Snack | H10: {=INT(VLOOKUP(OrderLines[[#This Row],[OrderID]:[OrderID]],Orders[],MATCH(OrderLines[[#Headers],[OrderDateTime]],Orders[#Headers],0),FALSE))} -> 45845 | I10: {=VLOOKUP(OrderLines[[#This Row],[OrderID]:[OrderID]],Orders[],MATCH(OrderLines[[#Headers],[Branch]],Orders[#Headers],0),FALSE)} -> Plant 2 Canteen | J10: {=VLOOKUP(OrderLines[[#This Row],[OrderID]:[OrderID]],Orders[],MATCH(OrderLines[[#Headers],[DiscountPct]],Orders[#Headers],0),FALSE)} -> 0.04 | K10: {=VLOOKUP(OrderLines[[#This Row],[OrderID]:[OrderID]],Orders[],MATCH(OrderLines[[#Headers],[PaymentType]],Orders[#Headers],0),FALSE)} -> Card | L10: {=VLOOKUP(OrderLines[[#This Row],[OrderID]:[OrderID]],Orders[],MATCH(OrderLines[[#Headers],[Shift]],Orders[#Headers],0),FALSE)} -> Breakfast | M10: =(OrderLines[[#This Row],[Qty]]*OrderLines[[#This Row],[UnitPrice]])*(1-OrderLines[[#This Row],[DiscountPct]]) -> 67.7184 | N10: =IF(AND(COUNTIFS(OrderLines[OrderID],OrderLines[[#This Row],[OrderID]],OrderLines[Category],"Hot Meal"),COUNTIFS(OrderLines[OrderID],OrderLines[[#This Row],[OrderID]],OrderLines[Category],"Beverage")),"Combo","Single") -> Single | O10: {=IF(SUMPRODUCT(OrderLines[UnitPrice],OrderLines[Qty],OrderLines[DiscountPct],--(OrderLines[OrderID] = OrderLines[[#This Row],[OrderID]]))>40,"High Discount","Ok")} -> Ok | P10: =OrderLines[[#This Row],[UnitCost]]*OrderLines[[#This Row],[Qty]] -> 35.81 | Q10: =OrderLines[[#This Row],[LineNetAmount]]-OrderLines[[#This Row],[Food Cost]] -> 31.9084
A11: O00005 | B11: B0T0PV | C11: 1 | D11: {=VLOOKUP(OrderLines[[#This Row],[SKU]:[SKU]],Menu[],MATCH(OrderLines[[#Headers],[UnitPrice]],Menu[#Headers],0),FALSE)} -> 28.43 | E11: {=VLOOKUP(OrderLines[[#This Row],[SKU]:[SKU]],Menu[],MATCH(OrderLines[[#Headers],[UnitCost]],Menu[#Headers],0),FALSE)} -> 13.89 | F11: {=VLOOKUP(OrderLines[[#This Row],[SKU]:[SKU]],Menu[],MATCH(OrderLines[[#Headers],[Category]],Menu[#Headers],0),FALSE)} -> Beverage | G11: {=_xlfn.TEXTJOIN("+",TRUE,_xlfn._xlws.SORT(_xlfn.UNIQUE(_xlfn._xlws.FILTER(OrderLines[Category],OrderLines[OrderID]=OrderLines[[#This Row],[OrderID]]))))} -> Beverage+Snack | H11: {=INT(VLOOKUP(OrderLines[[#This Row],[OrderID]:[OrderID]],Orders[],MATCH(OrderLines[[#Headers],[OrderDateTime]],Orders[#Headers],0),FALSE))} -> 45845 | I11: {=VLOOKUP(OrderLines[[#This Row],[OrderID]:[OrderID]],Orders[],MATCH(OrderLines[[#Headers],[Branch]],Orders[#Headers],0),FALSE)} -> Plant 2 Canteen | J11: {=VLOOKUP(OrderLines[[#This Row],[OrderID]:[OrderID]],Orders[],MATCH(OrderLines[[#Headers],[DiscountPct]],Orders[#Headers],0),FALSE)} -> 0.04 | K11: {=VLOOKUP(OrderLines[[#This Row],[OrderID]:[OrderID]],Orders[],MATCH(OrderLines[[#Headers],[PaymentType]],Orders[#Headers],0),FALSE)} -> Card | L11: {=VLOOKUP(OrderLines[[#This Row],[OrderID]:[OrderID]],Orders[],MATCH(OrderLines[[#Headers],[Shift]],Orders[#Headers],0),FALSE)} -> Breakfast | M11: =(OrderLines[[#This Row],[Qty]]*OrderLines[[#This Row],[UnitPrice]])*(1-OrderLines[[#This Row],[DiscountPct]]) -> 27.2928 | N11: =IF(AND(COUNTIFS(OrderLines[OrderID],OrderLines[[#This Row],[OrderID]],OrderLines[Category],"Hot Meal"),COUNTIFS(OrderLines[OrderID],OrderLines[[#This Row],[OrderID]],OrderLines[Category],"Beverage")),"Combo","Single") -> Single | O11: {=IF(SUMPRODUCT(OrderLines[UnitPrice],OrderLines[Qty],OrderLines[DiscountPct],--(OrderLines[OrderID] = OrderLines[[#This Row],[OrderID]]))>40,"High Discount","Ok")} -> Ok | P11: =OrderLines[[#This Row],[UnitCost]]*OrderLines[[#This Row],[Qty]] -> 13.89 | Q11: =OrderLines[[#This Row],[LineNetAmount]]-OrderLines[[#This Row],[Food Cost]] -> 13.4028
A12: O00006 | B12: BXO6QJ | C12: 3 | D12: {=VLOOKUP(OrderLines[[#This Row],[SKU]:[SKU]],Menu[],MATCH(OrderLines[[#Headers],[UnitPrice]],Menu[#Headers],0),FALSE)} -> 20.11 | E12: {=VLOOKUP(OrderLines[[#This Row],[SKU]:[SKU]],Menu[],MATCH(OrderLines[[#Headers],[UnitCost]],Menu[#Headers],0),FALSE)} -> 8 | F12: {=VLOOKUP(OrderLines[[#This Row],[SKU]:[SKU]],Menu[],MATCH(OrderLines[[#Headers],[Category]],Menu[#Headers],0),FALSE)} -> Beverage | G12: {=_xlfn.TEXTJOIN("+",TRUE,_xlfn._xlws.SORT(_xlfn.UNIQUE(_xlfn._xlws.FILTER(OrderLines[Category],OrderLines[OrderID]=OrderLines[[#This Row],[OrderID]]))))} -> Beverage | H12: {=INT(VLOOKUP(OrderLines[[#This Row],[OrderID]:[OrderID]],Orders[],MATCH(OrderLines[[#Headers],[OrderDateTime]],Orders[#Headers],0),FALSE))} -> 45863 | I12: {=VLOOKUP(OrderLines[[#This Row],[OrderID]:[OrderID]],Orders[],MATCH(OrderLines[[#Headers],[Branch]],Orders[#Headers],0),FALSE)} -> Plant 1 Canteen | J12: {=VLOOKUP(OrderLines[[#This Row],[OrderID]:[OrderID]],Orders[],MATCH(OrderLines[[#Headers],[DiscountPct]],Orders[#Headers],0),FALSE)} -> 0.1 | K12: {=VLOOKUP(OrderLines[[#This Row],[OrderID]:[OrderID]],Orders[],MATCH(OrderLines[[#Headers],[PaymentType]],Orders[#Headers],0),FALSE)} -> UPI | L12: {=VLOOKUP(OrderLines[[#This Row],[OrderID]:[OrderID]],Orders[],MATCH(OrderLines[[#Headers],[Shift]],Orders[#Headers],0),FALSE)} -> Breakfast | M12: =(OrderLines[[#This Row],[Qty]]*OrderLines[[#This Row],[UnitPrice]])*(1-OrderLines[[#This Row],[DiscountPct]]) -> 54.297 | N12: =IF(AND(COUNTIFS(OrderLines[OrderID],OrderLines[[#This Row],[OrderID]],OrderLines[Category],"Hot Meal"),COUNTIFS(OrderLines[OrderID],OrderLines[[#This Row],[OrderID]],OrderLines[Category],"Beverage")),"Combo","Single") -> Single | O12: {=IF(SUMPRODUCT(OrderLines[UnitPrice],OrderLines[Qty],OrderLines[DiscountPct],--(OrderLines[OrderID] = OrderLines[[#This Row],[OrderID]]))>40,"High Discount","Ok")} -> Ok | P12: =OrderLines[[#This Row],[UnitCost]]*OrderLines[[#This Row],[Qty]] -> 24 | Q12: =OrderLines[[#This Row],[LineNetAmount]]-OrderLines[[#This Row],[Food Cost]] -> 30.297
A13: O00007 | B13: BOC6UZ | C13: 1 | D13: {=VLOOKUP(OrderLines[[#This Row],[SKU]:[SKU]],Menu[],MATCH(OrderLines[[#Headers],[UnitPrice]],Menu[#Headers],0),FALSE)} -> 32.98 | E13: {=VLOOKUP(OrderLines[[#This Row],[SKU]:[SKU]],Menu[],MATCH(OrderLines[[#Headers],[UnitCost]],Menu[#Headers],0),FALSE)} -> 11.84 | F13: {=VLOOKUP(OrderLines[[#This Row],[SKU]:[SKU]],Menu[],MATCH(OrderLines[[#Headers],[Category]],Menu[#Headers],0),FALSE)} -> Beverage | G13: {=_xlfn.TEXTJOIN("+",TRUE,_xlfn._xlws.SORT(_xlfn.UNIQUE(_xlfn._xlws.FILTER(OrderLines[Category],OrderLines[OrderID]=OrderLines[[#This Row],[OrderID]]))))} -> Beverage+Hot Meal | H13: {=INT(VLOOKUP(OrderLines[[#This Row],[OrderID]:[OrderID]],Orders[],MATCH(OrderLines[[#Headers],[OrderDateTime]],Orders[#Headers],0),FALSE))} -> 45852 | I13: {=VLOOKUP(OrderLines[[#This Row],[OrderID]:[OrderID]],Orders[],MATCH(OrderLines[[#Headers],[Branch]],Orders[#Headers],0),FALSE)} -> Plant 2 Canteen | J13: {=VLOOKUP(OrderLines[[#This Row],[OrderID]:[OrderID]],Orders[],MATCH(OrderLines[[#Headers],[DiscountPct]],Orders[#Headers],0),FALSE)} -> 0.07 | K13: {=VLOOKUP(OrderLines[[#This Row],[OrderID]:[OrderID]],Orders[],MATCH(OrderLines[[#Headers],[PaymentType]],Orders[#Headers],0),FALSE)} -> Card | L13: {=VLOOKUP(OrderLines[[#This Row],[OrderID]:[OrderID]],Orders[],MATCH(OrderLines[[#Headers],[Shift]],Orders[#Headers],0),FALSE)} -> Dinner | M13: =(OrderLines[[#This Row],[Qty]]*OrderLines[[#This Row],[UnitPrice]])*(1-OrderLines[[#This Row],[DiscountPct]]) -> 30.6714 | N13: =IF(AND(COUNTIFS(OrderLines[OrderID],OrderLines[[#This Row],[OrderID]],OrderLines[Category],"Hot Meal"),COUNTIFS(OrderLines[OrderID],OrderLines[[#This Row],[OrderID]],OrderLines[Category],"Beverage")),"Combo","Single") -> Combo | O13: {=IF(SUMPRODUCT(OrderLines[UnitPrice],OrderLines[Qty],OrderLines[DiscountPct],--(OrderLines[OrderID] = OrderLines[[#This Row],[OrderID]]))>40,"High Discount","Ok")} -> Ok | P13: =OrderLines[[#This Row],[UnitCost]]*OrderLines[[#This Row],[Qty]] -> 11.84 | Q13: =OrderLines[[#This Row],[LineNetAmount]]-OrderLines[[#This Row],[Food Cost]] -> 18.8314
... A925: O00360 | B925: BTIQJ7 | C925: 2 | D925: {=VLOOKUP(OrderLines[[#This Row],[SKU]:[SKU]],Menu[],MATCH(OrderLines[[#Headers],[UnitPrice]],Menu[#Headers],0),FALSE)} -> 30.34 | E925: {=VLOOKUP(OrderLines[[#This Row],[SKU]:[SKU]],Menu[],MATCH(OrderLines[[#Headers],[UnitCost]],Menu[#Headers],0),FALSE)} -> 14.18 | F925: {=VLOOKUP(OrderLines[[#This Row],[SKU]:[SKU]],Menu[],MATCH(OrderLines[[#Headers],[Category]],Menu[#Headers],0),FALSE)} -> Beverage | G925: {=_xlfn.TEXTJOIN("+",TRUE,_xlfn._xlws.SORT(_xlfn.UNIQUE(_xlfn._xlws.FILTER(OrderLines[Category],OrderLines[OrderID]=OrderLines[[#This Row],[OrderID]]))))} -> Beverage+Hot Meal | H925: {=INT(VLOOKUP(OrderLines[[#This Row],[OrderID]:[OrderID]],Orders[],MATCH(OrderLines[[#Headers],[OrderDateTime]],Orders[#Headers],0),FALSE))} -> 45878 | I925: {=VLOOKUP(OrderLines[[#This Row],[OrderID]:[OrderID]],Orders[],MATCH(OrderLines[[#Headers],[Branch]],Orders[#Headers],0),FALSE)} -> Plant 2 Canteen | J925: {=VLOOKUP(OrderLines[[#This Row],[OrderID]:[OrderID]],Orders[],MATCH(OrderLines[[#Headers],[DiscountPct]],Orders[#Headers],0),FALSE)} -> 0.04 | K925: {=VLOOKUP(OrderLines[[#This Row],[OrderID]:[OrderID]],Orders[],MATCH(OrderLines[[#Headers],[PaymentType]],Orders[#Headers],0),FALSE)} -> UPI | L925: {=VLOOKUP(OrderLines[[#This Row],[OrderID]:[OrderID]],Orders[],MATCH(OrderLines[[#Headers],[Shift]],Orders[#Headers],0),FALSE)} -> Dinner | M925: =(OrderLines[[#This Row],[Qty]]*OrderLines[[#This Row],[UnitPrice]])*(1-OrderLines[[#This Row],[DiscountPct]]) -> 58.2528 | N925: =IF(AND(COUNTIFS(OrderLines[OrderID],OrderLines[[#This Row],[OrderID]],OrderLines[Category],"Hot Meal"),COUNTIFS(OrderLines[OrderID],OrderLines[[#This Row],[OrderID]],OrderLines[Category],"Beverage")),"Combo","Single") -> Combo | O925: {=IF(SUMPRODUCT(OrderLines[UnitPrice],OrderLines[Qty],OrderLines[DiscountPct],--(OrderLines[OrderID] = OrderLines[[#This Row],[OrderID]]))>40,"High Discount","Ok")} -> High Discount | P925: =OrderLines[[#This Row],[UnitCost]]*OrderLines[[#This Row],[Qty]] -> 28.36 | Q925: =OrderLines[[#This Row],[LineNetAmount]]-OrderLines[[#This Row],[Food Cost]] -> 29.8928

Sheet pivot charts
A1: 1 | B1: total combo orders | D1: all orders
B2: {=COUNTA(_xlfn.UNIQUE(_xlfn._xlws.FILTER(OrderLines[OrderID],OrderLines[Combo Flag]="Combo")))} -> 86 | D2: =COUNTA(_xlfn.UNIQUE(OrderLines[OrderID])) -> 360
C4: combo order as % of all order
C5: =B2/D2 -> 0.23888889
A8: combo rev | B8: =SUMIFS(OrderLines[LineNetAmount],OrderLines[Combo Flag],"Combo") -> 46800.541
A9: avg tkt size | B9: {=SUMIFS(OrderLines[LineNetAmount],OrderLines[Combo Flag],"Combo")/COUNTA(_xlfn.UNIQUE(_xlfn._xlws.FILTER(OrderLines[OrderID],OrderLines[Combo Flag]="Combo")))} -> 544.19233
A11: combo profit | B11: =SUMIFS(OrderLines[Gross Profit],OrderLines[Combo Flag],"Combo") -> 23976.601
A12: avg gp/combo order | B12: {=SUMIFS(OrderLines[Gross Profit],OrderLines[Combo Flag],"Combo")/COUNTA(_xlfn.UNIQUE(_xlfn._xlws.FILTER(OrderLines[OrderID],OrderLines[Combo Flag]="Combo")))} -> 278.79768
A17: 2 | B17: Combo flag | C17: total rev | D17: orderid count | E17: avg tkt size | F17: avg total foodcost | G17: avg gp | H17: Gross margin% | M17: Row Labels | N17: Sum of LineNetAmount | O17: Sum of Food Cost | P17: Sum of Gross Profit | Q17: Distinct Count of OrderID
B18: Combo | C18: =SUMIFS(OrderLines[LineNetAmount],OrderLines[Combo Flag],B18) -> 46800.541 | D18: {=COUNTA(_xlfn.UNIQUE(_xlfn._xlws.FILTER(OrderLines[OrderID],OrderLines[Combo Flag]=B18)))} -> 86 | E18: {=SUMIFS(OrderLines[LineNetAmount],OrderLines[Combo Flag],B18)/COUNTA(_xlfn.UNIQUE(_xlfn._xlws.FILTER(OrderLines[OrderID],OrderLines[Combo Flag]=B18)))} -> 544.19233 | F18: {=SUMIFS(OrderLines[Food Cost],OrderLines[Combo Flag],B18)/COUNTA(_xlfn.UNIQUE(_xlfn._xlws.FILTER(OrderLines[OrderID],OrderLines[Combo Flag]=B18)))} -> 265.39465 | G18: {=SUMIFS(OrderLines[Gross Profit],OrderLines[Combo Flag],B18)/COUNTA(_xlfn.UNIQUE(_xlfn._xlws.FILTER(OrderLines[OrderID],OrderLines[Combo Flag]=B18)))} -> 278.79768 | H18: =SUMIFS(OrderLines[Gross Profit],OrderLines[Combo Flag],B18)/SUMIFS(OrderLines[LineNetAmount],OrderLines[Combo Flag],B18) -> 0.51231461 | M18: Combo | N18: 46800.541 | O18: 22823.94 | P18: 23976.601 | Q18: 86
B19: Single | C19: =SUMIFS(OrderLines[LineNetAmount],OrderLines[Combo Flag],B19) -> 85847.09 | D19: {=COUNTA(_xlfn.UNIQUE(_xlfn._xlws.FILTER(OrderLines[OrderID],OrderLines[Combo Flag]=B19)))} -> 274 | E19: {=SUMIFS(OrderLines[LineNetAmount],OrderLines[Combo Flag],B19)/COUNTA(_xlfn.UNIQUE(_xlfn._xlws.FILTER(OrderLines[OrderID],OrderLines[Combo Flag]=B19)))} -> 313.31055 | F19: {=SUMIFS(OrderLines[Food Cost],OrderLines[Combo Flag],B19)/COUNTA(_xlfn.UNIQUE(_xlfn._xlws.FILTER(OrderLines[OrderID],OrderLines[Combo Flag]=B19)))} -> 154.47212 | G19: {=SUMIFS(OrderLines[Gross Profit],OrderLines[Combo Flag],B19)/COUNTA(_xlfn.UNIQUE(_xlfn._xlws.FILTER(OrderLines[OrderID],OrderLines[Combo Flag]=B19)))} -> 158.83843 | H19: =SUMIFS(OrderLines[Gross Profit],OrderLines[Combo Flag],B19)/SUMIFS(OrderLines[LineNetAmount],OrderLines[Combo Flag],B19) -> 0.50696803 | M19: Single | N19: 85847.09 | O19: 42325.36 | P19: 43521.73 | Q19: 274
B20: Gap | C20: =C18-C19 -> -39046.549 | D20: =D18-D19 -> -188 | E20: =E18-E19 -> 230.88179 | F20: =F18-F19 -> 110.92253 | G20: =G18-G19 -> 119.95925 | H20: =H18-H19 -> 0.0053465805 | M20: Grand Total | N20: 132647.63 | O20: 65149.3 | P20: 67498.331 | Q20: 360
N22: Avg Tkt Size | O22: Avg Food Cost | P22: Avg Gross Profit | Q22: gm%
M23: Combo | N23: =N18/$Q18 -> 544.19233 | O23: =O18/$Q18 -> 265.39465 | P23: =P18/$Q18 -> 278.79768 | Q23: =P18/N18 -> 0.51231461
M24: Single | N24: =N19/$Q19 -> 313.31055 | O24: =O19/$Q19 -> 154.47212 | P24: =P19/$Q19 -> 158.83843 | Q24: =P19/N19 -> 0.50696803
M25: Gap | N25: =N23-N24 -> 230.88179 | O25: =O23-O24 -> 110.92253 | P25: =P23-P24 -> 119.95925 | Q25: =Q23-Q24 -> 0.0053465805
N30: Gross margin%
M31: Combo | N31: =Q23 -> 0.51231461
M32: Single | N32: =Q24 -> 0.50696803
M33: Gap | N33: =Q25 -> 0.0053465805
A38: 4 | B38: Distinct Count of OrderID | C38: Column Labels
B39: Row Labels | C39: Combo
B40: Breakfast | C40: 1
B41: Grand Total | C41: 1
A47: 3 | B47: Distinct Count of OrderID | C47: Column Labels
B48: Row Labels | C48: Combo
B49: Plant 1 Canteen | C49: 0.1744186
B50: Head Office Café | C50: 0.40697674
B51: Plant 2 Canteen | C51: 0.41860465
B52: Grand Total | C52: 1
A56: 5 | B56: Categories Combination | C56: Orders | E56: Categories Combination | F56: Orders
B57: Beverage | C57: 34 | E57: =B57 -> Beverage | F57: =C57 -> 34
B58: Beverage+Snack | C58: 31 | E58: =B58 -> Beverage+Snack | F58: =C58 -> 31
B59: Snack | C59: 29 | E59: =B59 -> Snack | F59: =C59 -> 29
B60: Hot Meal+Snack | C60: 28 | E60: =B60 -> Hot Meal+Snack | F60: =C60 -> 28
B61: Hot Meal | C61: 27 | E61: =B61 -> Hot Meal | F61: =C61 -> 27
B62: Dessert+Hot Meal | C62: 27 | E62: =B62 -> Dessert+Hot Meal | F62: =C62 -> 27
B63: Beverage+Dessert+Hot Meal | C63: 27 | E63: =B63 -> Beverage+Dessert+Hot Meal | F63: =C63 -> 27
B64: Beverage+Hot Meal+Snack | C64: 25 | E64: =B64 -> Beverage+Hot Meal+Snack | F64: =C64 -> 25
B65: Beverage+Hot Meal | C65: 25 | E65: =B65 -> Beverage+Hot Meal | F65: =C65 -> 25
B66: Beverage+Dessert | C66: 23 | E66: =B66 -> Beverage+Dessert | F66: =C66 -> 23
B67: Dessert+Hot Meal+Snack | C67: 23 | E67: =B67 -> Dessert+Hot Meal+Snack | F67: =C67 -> 23
B68: Beverage+Dessert+Snack | C68: 22 | E68: =B68 -> Beverage+Dessert+Snack | F68: =C68 -> 22
... B71: Beverage+Dessert+Hot Meal+Snack | C71: 9 | E71: =B71 -> Beverage+Dessert+Hot Meal+Snack | F71: =C71 -> 9
A74: 6 | C74: Hot Meal | D74: Beverage | E74: Discount %
C75: Rajma Chawal | D75: Bottled Water | E75: 0.05
C77: food cost | D77: Net selling price | E77: gross profit | F77: GM% | G77: Bev stock
C78: {=SUM(_xlfn._xlws.FILTER(Menu[UnitCost],Menu[ItemName]=C75),_xlfn._xlws.FILTER(Menu[UnitCost],Menu[ItemName]=D75))} -> 94.81 | D78: {=(SUM(_xlfn._xlws.FILTER(Menu[UnitPrice],Menu[ItemName]=C75),_xlfn._xlws.FILTER(Menu[UnitPrice],Menu[ItemName]=D75)))*(1-E75)} -> 166.0885 | E78: =D78-C78 -> 71.2785 | F78: =E78/D78 -> 0.42915976 | G78: =_xlfn.XLOOKUP(D75,Inventory[ItemName],Inventory[OnHandQty],"Not Available",0) -> 199
D87: new kpis
B90: combo flag | C90: combo
I91: Row Labels | J91: Average of Revenue | M91: Row Labels | N91: Average of profit | P91: Count of OrderID
B92: Count of OrderID | E92: Row Labels | F92: Count of OrderID | I92: combo | J92: 544.19233 | M92: combo | N92: 278.79768 | P92: 360
B93: 86 | E93: combo | F93: 0.23888889 | I93: single | J93: 313.31055 | M93: single | N93: 158.83843
E94: single | F94: 0.76111111 | I94: Grand Total | J94: 368.46564 | M94: Grand Total | N94: 187.49536
E95: Grand Total | F95: 1
C102: Column Labels
B103: Values | C103: combo | D103: single
B104: Average of Revenue | C104: 544.19233 | D104: 313.31055 | E104: =(C104-D104)/D104 -> 0.73691036
B105: Average of total cost | C105: 265.39465 | D105: 154.47212 | E105: =(C105-D105)/D105 -> 0.7180748
B106: Average of profit | C106: 278.79768 | D106: 158.83843 | E106: =(C106-D106)/D106 -> 0.75522814
B107: Sum of gm% | C107: 0.51231461 | D107: 0.50696803 | E107: =C107-D107 -> 0.0053465805
B113: Count of OrderID | C113: Column Labels
B114: Row Labels | C114: combo | D114: single
B115: Head Office Café | C115: 0.2892562 | D115: 0.7107438
B116: Plant 1 Canteen | C116: 0.13761468 | D116: 0.86238532
B117: Plant 2 Canteen | C117: 0.27692308 | D117: 0.72307692
B123: Count of OrderID | C123: Column Labels
B124: Row Labels | C124: combo | D124: single
B125: Breakfast | C125: 0.2259887 | D125: 0.7740113
B126: Dinner | C126: 0.28181818 | D126: 0.71818182
B127: Lunch | C127: 0.20547945 | D127: 0.79452055
B132: Row Labels | C132: Count of Item list
B133: Beverage | C133: 34
B134: Beverage+Snack | C134: 31
B135: Snack | C135: 29
B136: Hot Meal+Snack | C136: 28
B137: Hot Meal | C137: 27
B138: Dessert+Hot Meal | C138: 27
B139: Beverage+Dessert+Hot Meal | C139: 27
B140: Beverage+Hot Meal+Snack | C140: 25
B141: Beverage+Hot Meal | C141: 25
B142: Beverage+Dessert | C142: 23
B143: Dessert+Hot Meal+Snack | C143: 23
B144: Beverage+Dessert+Snack | C144: 22
... B147: Beverage+Dessert+Hot Meal+Snack | C147: 9

Sheet Dashboard
A2: FOOD & BEVERAGE BUSINESS PERFORMANCE DASHBOARD (JULY-AUGUST 2025)
B6: Combo Orders | G6: Combo Orders % | L6: Avg Ticket Size | Q6: Avg Gross Profit/Combo | V6: Total Orders | AA6: Gross Margin%
B8: ='pivot charts'!B93 -> 86 | G8: ='pivot charts'!F93 -> 0.23888889 | L8: ='pivot charts'!J92 -> 544.19233 | Q8: ='pivot charts'!N92 -> 278.79768 | V8: ='pivot charts'!P92 -> 360 | AA8: ='pivot charts'!C107 -> 0.51231461
O27: INTERACTIVE PROFITABILITY SIMULATOR | AF27: Values | AG27: Combo | AH27: Single | AI27: Difference %
AF29: Avg Revenue | AG29: ='pivot charts'!C104 -> 544.19233 | AH29: ='pivot charts'!D104 -> 313.31055 | AI29: ='pivot charts'!E104 -> 0.73691036
P30: SELECT A HOT MEAL | U30: SELECT A BEVERAGE | Z30: ENTER A DISCOUNT%
AF31: Avg Cost | AG31: ='pivot charts'!C105 -> 265.39465 | AH31: ='pivot charts'!D105 -> 154.47212 | AI31: ='pivot charts'!E105 -> 0.7180748
P32: Rajma Chawal | U32: Bottled Water | Z32: 0.05
AF33: Avg Profit | AG33: ='pivot charts'!C106 -> 278.79768 | AH33: ='pivot charts'!D106 -> 158.83843 | AI33: ='pivot charts'!E106 -> 0.75522814
P35: FOOD COST | U35: NET SELLING PRICE | Z35: GROSS PROFIT | AF35: GM% | AG35: ='pivot charts'!C107 -> 0.51231461 | AH35: ='pivot charts'!D107 -> 0.50696803 | AI35: ='pivot charts'!E107 -> 0.0053465805
P37: {=SUM(_xlfn._xlws.FILTER(Menu[UnitCost],Menu[ItemName]=$P$32),_xlfn._xlws.FILTER(Menu[UnitCost],Menu[ItemName]=$U$32))} -> 94.81 | U37: {=(SUM(_xlfn._xlws.FILTER(Menu[UnitPrice],Menu[ItemName]=$P$32),_xlfn._xlws.FILTER(Menu[UnitPrice],Menu[ItemName]=$U$32)))*(1-$Z$32)} -> 166.0885 | Z37: =$U$37-$P$37 -> 71.2785
AF38: Combo Vs Single
R40: GROSS MARGIN% | X40: CURRENT BEVERAGE STOCK
R42: =$Z$37/$U$37 -> 0.42915976 | X42: =_xlfn.XLOOKUP($U$32,Inventory[ItemName],Inventory[OnHandQty],"Not Available",0) -> 199

Sheet Day 2 Ans
B1: 1 | C1: Line net amount | D1: =SUM(OrderLines[LineNetAmount]) -> 132647.63
L3: Row Labels | M3: Sum of Revenue2 | N3: Sum of Revenue
B4: 2 | C4: July revenue | D4: =SUMIFS(OrderLines[LineNetAmount],OrderLines[OrderDateTime],">=2025-7-1",OrderLines[OrderDateTime],"<=2025-7-31") -> 63939.191 | F4: MOM% | G4: =(D5-D4)/D4 -> 0.07459039 | L4: Jul | M4: 63939.191
C5: August revenue | D5: =SUMIFS(OrderLines[LineNetAmount],OrderLines[OrderDateTime],">=2025-8-1",OrderLines[OrderDateTime],"<=2025-8-31") -> 68708.44 | L5: Aug | M5: 68708.44 | N5: 0.07459039
L7: Shift | M7: (All)
L8: Branch | M8: (All)
B9: 3 | C9: =SUMIFS(OrderLines[LineNetAmount],OrderLines[Branch],"Head Office Café",OrderLines[Shift],"Lunch",OrderLines[OrderDateTime],">=2025-08-01",OrderLines[OrderDateTime],"<=2025-08-31") -> 7403.6595
L10: Row Labels | M10: Sum of Revenue
L11: Aug | M11: 68708.44
B13: 4 | C13: {=COUNTA(_xlfn.UNIQUE(_xlfn._xlws.FILTER(OrderLines[OrderID],(OrderLines[Category]="Beverage")*(OrderLines[PaymentType]="UPI"))))} -> 70 | L13: has beverage | M13: yes
L15: Row Labels | M15: Count of OrderID
C16: Shift | L16: UPI | M16: 70
B17: 5 | C17: Breakfast | D17: {=SUMIFS(OrderLines[LineNetAmount],OrderLines[Shift],C17)/COUNTA(_xlfn.UNIQUE(_xlfn._xlws.FILTER(OrderLines[OrderID],OrderLines[Shift]=C17)))} -> 360.57145
C18: Lunch | D18: {=SUMIFS(OrderLines[LineNetAmount],OrderLines[Shift],C18)/COUNTA(_xlfn.UNIQUE(_xlfn._xlws.FILTER(OrderLines[OrderID],OrderLines[Shift]=C18)))} -> 372.02587
C19: Dinner | D19: {=SUMIFS(OrderLines[LineNetAmount],OrderLines[Shift],C19)/COUNTA(_xlfn.UNIQUE(_xlfn._xlws.FILTER(OrderLines[OrderID],OrderLines[Shift]=C19)))} -> 378.80541
M20: Row Labels | N20: Average of Revenue
M21: Breakfast | N21: 360.57145
M22: Dinner | N22: 378.80541
M23: Lunch | N23: 372.02587

Sheet Day 4 Ans
A2: 1
B3: Branch | C3: Values
B4: Head Office Café | D4: Plant 1 Canteen | F4: Plant 2 Canteen
A5: Category | B5: Revenue | C5: Sum of LineNetAmount | D5: Revenue | E5: Sum of LineNetAmount | F5: Revenue | G5: Sum of LineNetAmount
A6: Beverage | B6: 0.071247851 | C6: 3489.8727 | D6: 0.087079621 | E6: 2895.3357 | F6: 0.078081063 | G6: 3936.5499
A7: Dessert | B7: 0.19484685 | C7: 9544.0172 | D7: 0.19542264 | E7: 6497.6642 | F7: 0.16888445 | G7: 8514.5112
A8: Hot Meal | B8: 0.62481557 | C8: 30604.808 | D8: 0.52355178 | E8: 17407.726 | F8: 0.61734407 | G8: 31124.138
A9: Snack | B9: 0.10908973 | C9: 5343.449 | D9: 0.19394596 | E9: 6448.5657 | F9: 0.13569041 | G9: 6840.9941
A10: Grand Total | B10: 1 | C10: 48982.147 | D10: 1 | E10: 33249.291 | F10: 1 | G10: 50416.193
A12: 2
A13: Month | B13: Aug | G13: 3
G14: Branch | H14: GM% | I14: Sum of LineNetAmount
A15: SKU | B15: Revenue | C15: Quantity | G15: Head Office Café | H15: 0.50999942 | I15: 48982.147
A16: HXAJI0 | B16: 10470.06 | C16: 49 | G16: Plant 1 Canteen | H16: 0.4971165 | I16: 33249.291
A17: HDPBHS | B17: 9230.7763 | C17: 38 | G17: Plant 2 Canteen | H17: 0.51548305 | I17: 50416.193
A18: HH1DNM | B18: 8283.3894 | C18: 36
A19: HUZZPQ | B19: 6563.112 | C19: 48
A20: H3A3ZM | B20: 5927.801 | C20: 37
A21: D9T84A | B21: 4925.456 | C21: 45
A22: DH9SDB | B22: 3714.9715 | C22: 52
A23: SCKW5N | B23: 2910.4804 | C23: 44
A24: DFFYVN | B24: 2362.578 | C24: 46
A25: S5NQ4F | B25: 2318.778 | C25: 49
A26: Grand Total | B26: 56707.403 | C26: 444

Sheet Daily Summary
B1: Date | C1: Revenue | D1: Avg Feedback Rating | E1: Avg waste cost
B2: {=_xlfn.SEQUENCE(DATEDIF(DATE(2025,7,1),DATE(2025,8,31),"d")+1,1,DATE(2025,7,1),1)} -> 45839 | C2: =SUMIFS(OrderLines[LineNetAmount],OrderLines[OrderDateTime],$B2) -> 198.822 | D2: =IFERROR(AVERAGEIFS(Feedback[Rating],Feedback[Date],$B2),0) -> 3.8571429 | E2: =IFERROR(ROUND(AVERAGEIFS(WasteLog[Waste cost],WasteLog[Date],$B2),2),0) -> 0
B3: 45840 | C3: =SUMIFS(OrderLines[LineNetAmount],OrderLines[OrderDateTime],$B3) -> 3202.85 | D3: =IFERROR(AVERAGEIFS(Feedback[Rating],Feedback[Date],$B3),0) -> 3.6 | E3: =IFERROR(ROUND(AVERAGEIFS(WasteLog[Waste cost],WasteLog[Date],$B3),2),0) -> 92.48
B4: 45841 | C4: =SUMIFS(OrderLines[LineNetAmount],OrderLines[OrderDateTime],$B4) -> 1027.7541 | D4: =IFERROR(AVERAGEIFS(Feedback[Rating],Feedback[Date],$B4),0) -> 4 | E4: =IFERROR(ROUND(AVERAGEIFS(WasteLog[Waste cost],WasteLog[Date],$B4),2),0) -> 0
B5: 45842 | C5: =SUMIFS(OrderLines[LineNetAmount],OrderLines[OrderDateTime],$B5) -> 1622.0684 | D5: =IFERROR(AVERAGEIFS(Feedback[Rating],Feedback[Date],$B5),0) -> 4.5 | E5: =IFERROR(ROUND(AVERAGEIFS(WasteLog[Waste cost],WasteLog[Date],$B5),2),0) -> 80.92
B6: 45843 | C6: =SUMIFS(OrderLines[LineNetAmount],OrderLines[OrderDateTime],$B6) -> 626.2479 | D6: =IFERROR(AVERAGEIFS(Feedback[Rating],Feedback[Date],$B6),0) -> 4 | E6: =IFERROR(ROUND(AVERAGEIFS(WasteLog[Waste cost],WasteLog[Date],$B6),2),0) -> 84.55
B7: 45844 | C7: =SUMIFS(OrderLines[LineNetAmount],OrderLines[OrderDateTime],$B7) -> 2758.1276 | D7: =IFERROR(AVERAGEIFS(Feedback[Rating],Feedback[Date],$B7),0) -> 3.5 | E7: =IFERROR(ROUND(AVERAGEIFS(WasteLog[Waste cost],WasteLog[Date],$B7),2),0) -> 108.7
B8: 45845 | C8: =SUMIFS(OrderLines[LineNetAmount],OrderLines[OrderDateTime],$B8) -> 1619.6286 | D8: =IFERROR(AVERAGEIFS(Feedback[Rating],Feedback[Date],$B8),0) -> 4.75 | E8: =IFERROR(ROUND(AVERAGEIFS(WasteLog[Waste cost],WasteLog[Date],$B8),2),0) -> 74.07
B9: 45846 | C9: =SUMIFS(OrderLines[LineNetAmount],OrderLines[OrderDateTime],$B9) -> 425.1991 | D9: =IFERROR(AVERAGEIFS(Feedback[Rating],Feedback[Date],$B9),0) -> 4 | E9: =IFERROR(ROUND(AVERAGEIFS(WasteLog[Waste cost],WasteLog[Date],$B9),2),0) -> 35.32
B10: 45847 | C10: =SUMIFS(OrderLines[LineNetAmount],OrderLines[OrderDateTime],$B10) -> 2706.5737 | D10: =IFERROR(AVERAGEIFS(Feedback[Rating],Feedback[Date],$B10),0) -> 3.1666667 | E10: =IFERROR(ROUND(AVERAGEIFS(WasteLog[Waste cost],WasteLog[Date],$B10),2),0) -> 37.26
B11: 45848 | C11: =SUMIFS(OrderLines[LineNetAmount],OrderLines[OrderDateTime],$B11) -> 3654.4446 | D11: =IFERROR(AVERAGEIFS(Feedback[Rating],Feedback[Date],$B11),0) -> 4 | E11: =IFERROR(ROUND(AVERAGEIFS(WasteLog[Waste cost],WasteLog[Date],$B11),2),0) -> 8
B12: 45849 | C12: =SUMIFS(OrderLines[LineNetAmount],OrderLines[OrderDateTime],$B12) -> 3744.4975 | D12: =IFERROR(AVERAGEIFS(Feedback[Rating],Feedback[Date],$B12),0) -> 3.5 | E12: =IFERROR(ROUND(AVERAGEIFS(WasteLog[Waste cost],WasteLog[Date],$B12),2),0) -> 195.31
B13: 45850 | C13: =SUMIFS(OrderLines[LineNetAmount],OrderLines[OrderDateTime],$B13) -> 3559.4395 | D13: =IFERROR(AVERAGEIFS(Feedback[Rating],Feedback[Date],$B13),0) -> 4 | E13: =IFERROR(ROUND(AVERAGEIFS(WasteLog[Waste cost],WasteLog[Date],$B13),2),0) -> 143.24
B14: 45851 | C14: =SUMIFS(OrderLines[LineNetAmount],OrderLines[OrderDateTime],$B14) -> 2567.5368 | D14: =IFERROR(AVERAGEIFS(Feedback[Rating],Feedback[Date],$B14),0) -> 3.8 | E14: =IFERROR(ROUND(AVERAGEIFS(WasteLog[Waste cost],WasteLog[Date],$B14),2),0) -> 0
... B63: 45900 | C63: =SUMIFS(OrderLines[LineNetAmount],OrderLines[OrderDateTime],$B63) -> 0 | D63: =IFERROR(AVERAGEIFS(Feedback[Rating],Feedback[Date],$B63),0) -> 0 | E63: =IFERROR(ROUND(AVERAGEIFS(WasteLog[Waste cost],WasteLog[Date],$B63),2),0) -> 0

Sheet Menu (Day 6 Ans)
A1: SKU | B1: ItemName | C1: Category | D1: SupplierID | E1: UnitCost | F1: UnitPrice
A2: HXAJI0 | B2: Veg Thali | C2: Hot Meal | D2: S009 | E2: 96.22 | F2: 227.61
A3: HDPBHS | B3: Chicken Thali | C3: Hot Meal | D3: S001 | E3: 121.24 | F3: 256.91 | J3: SKU | K3: UnitCost
A4: HUZZPQ | B4: Rajma Chawal | C4: Hot Meal | D4: S005 | E4: 80.92 | F4: 146.4
A5: H3A3ZM | B5: Paneer Butter Masala + Naan | C5: Hot Meal | D5: S003 | E5: 74.07 | F5: 170.83 | J5: BOC6UZ | K5: =VLOOKUP($J$5,Menu[],MATCH($K$3,Menu[#Headers],0),FALSE) -> 11.84
A6: HH1DNM | B6: Egg Curry + Rice | C6: Hot Meal | D6: S006 | E6: 112.08 | F6: 246.09
A7: SV30T9 | B7: Samosa | C7: Snack | D7: S007 | E7: 15.51 | F7: 39.95
A8: SCKW5N | B8: Veg Sandwich | C8: Snack | D8: S004 | E8: 35.81 | F8: 70.54
A9: SZBIKC | B9: Paneer Roll | C9: Snack | D9: S004 | E9: 19.55 | F9: 38.06
A10: S5NQ4F | B10: Masala Puff | C10: Snack | D10: S006 | E10: 22.61 | F10: 50.19
A11: SHJ7XV | B11: Poha | C11: Snack | D11: S003 | E11: 25.8 | F11: 52.45
A12: BTIQJ7 | B12: Tea | C12: Beverage | D12: S009 | E12: 14.18 | F12: 30.34
A13: BHL1C3 | B13: Coffee | C13: Beverage | D13: S006 | E13: 9.38 | F13: 22.2
A14: BOC6UZ | B14: Masala Chaas | C14: Beverage | D14: S004 | E14: 11.84 | F14: 32.98
A15: BXO6QJ | B15: Nimbu Pani | C15: Beverage | D15: S004 | E15: 8 | F15: 20.11
A16: B0T0PV | B16: Bottled Water | C16: Beverage | D16: S006 | E16: 13.89 | F16: 28.43
A17: DH9SDB | B17: Gulab Jamun (2 pc) | C17: Dessert | D17: S002 | E17: 38.23 | F17: 76.55
... A20: DYTJXE | B20: Fruit Cup | C20: Dessert | D20: S007 | E20: 29.14 | F20: 57.07

Sheet Staff
A1: StaffID | B1: StaffName | C1: Role | D1: Branch | E1: HourlyRateINR
A2: E001 | B2: Tarun | C2: Cashier | D2: Plant 1 Canteen | E2: 151.58
A3: E002 | B3: Payal | C3: Cashier | D3: Head Office Café | E3: 129.61
A4: E003 | B4: Karan | C4: Cashier | D4: Head Office Café | E4: 100.98
A5: E004 | B5: Payal | C5: Cook | D5: Plant 1 Canteen | E5: 134.57
A6: E005 | B6: Vikram | C6: Cook | D6: Head Office Café | E6: 93.09
A7: E006 | B7: Rina | C7: Cashier | D7: Head Office Café | E7: 171.84
A8: E007 | B8: Sanjay | C8: Cook | D8: Plant 2 Canteen | E8: 113.29
A9: E008 | B9: Manish | C9: Cook | D9: Head Office Café | E9: 149.63
A10: E009 | B10: Pooja | C10: Server | D10: Head Office Café | E10: 118.05
A11: E010 | B11: Sourav | C11: Cashier | D11: Plant 1 Canteen | E11: 136.81
A12: E011 | B12: Neha | C12: Cashier | D12: Plant 2 Canteen | E12: 139.2
A13: E012 | B13: Amit | C13: Cook | D13: Head Office Café | E13: 106.64
... A19: E018 | B19: Payal | C19: Cashier | D19: Head Office Café | E19: 172.97

Sheet Inventory
A1: SKU | B1: OnHandQty | C1: ReorderPoint | D1: LeadTimeDays | E1: LastRestockDate | F1: ItemName
A2: HXAJI0 | B2: 198 | C2: 36 | D2: 3 | E2: 45876 | F2: =VLOOKUP(Inventory[[#This Row],[SKU]],Menu[],MATCH(Inventory[[#Headers],[ItemName]],Menu[#Headers],0),FALSE) -> Veg Thali
A3: HDPBHS | B3: 152 | C3: 30 | D3: 6 | E3: 45861 | F3: =VLOOKUP(Inventory[[#This Row],[SKU]],Menu[],MATCH(Inventory[[#Headers],[ItemName]],Menu[#Headers],0),FALSE) -> Chicken Thali
A4: HUZZPQ | B4: 120 | C4: 25 | D4: 6 | E4: 45882 | F4: =VLOOKUP(Inventory[[#This Row],[SKU]],Menu[],MATCH(Inventory[[#Headers],[ItemName]],Menu[#Headers],0),FALSE) -> Rajma Chawal
A5: H3A3ZM | B5: 130 | C5: 42 | D5: 4 | E5: 45864 | F5: =VLOOKUP(Inventory[[#This Row],[SKU]],Menu[],MATCH(Inventory[[#Headers],[ItemName]],Menu[#Headers],0),FALSE) -> Paneer Butter Masala + Naan
A6: HH1DNM | B6: 176 | C6: 46 | D6: 3 | E6: 45871 | F6: =VLOOKUP(Inventory[[#This Row],[SKU]],Menu[],MATCH(Inventory[[#Headers],[ItemName]],Menu[#Headers],0),FALSE) -> Egg Curry + Rice
A7: SV30T9 | B7: 81 | C7: 25 | D7: 3 | E7: 45868 | F7: =VLOOKUP(Inventory[[#This Row],[SKU]],Menu[],MATCH(Inventory[[#Headers],[ItemName]],Menu[#Headers],0),FALSE) -> Samosa
A8: SCKW5N | B8: 45 | C8: 57 | D8: 4 | E8: 45840 | F8: =VLOOKUP(Inventory[[#This Row],[SKU]],Menu[],MATCH(Inventory[[#Headers],[ItemName]],Menu[#Headers],0),FALSE) -> Veg Sandwich
A9: SZBIKC | B9: 89 | C9: 21 | D9: 5 | E9: 45864 | F9: =VLOOKUP(Inventory[[#This Row],[SKU]],Menu[],MATCH(Inventory[[#Headers],[ItemName]],Menu[#Headers],0),FALSE) -> Paneer Roll
A10: S5NQ4F | B10: 85 | C10: 41 | D10: 3 | E10: 45873 | F10: =VLOOKUP(Inventory[[#This Row],[SKU]],Menu[],MATCH(Inventory[[#Headers],[ItemName]],Menu[#Headers],0),FALSE) -> Masala Puff
A11: SHJ7XV | B11: 80 | C11: 39 | D11: 2 | E11: 45861 | F11: =VLOOKUP(Inventory[[#This Row],[SKU]],Menu[],MATCH(Inventory[[#Headers],[ItemName]],Menu[#Headers],0),FALSE) -> Poha
A12: BTIQJ7 | B12: 84 | C12: 44 | D12: 4 | E12: 45845 | F12: =VLOOKUP(Inventory[[#This Row],[SKU]],Menu[],MATCH(Inventory[[#Headers],[ItemName]],Menu[#Headers],0),FALSE) -> Tea
A13: BHL1C3 | B13: 55 | C13: 34 | D13: 3 | E13: 45850 | F13: =VLOOKUP(Inventory[[#This Row],[SKU]],Menu[],MATCH(Inventory[[#Headers],[ItemName]],Menu[#Headers],0),FALSE) -> Coffee
... A20: DYTJXE | B20: 53 | C20: 58 | D20: 5 | E20: 45850 | F20: =VLOOKUP(Inventory[[#This Row],[SKU]],Menu[],MATCH(Inventory[[#Headers],[ItemName]],Menu[#Headers],0),FALSE) -> Fruit Cup

Sheet Suppliers
A1: SupplierID | B1: SupplierName | C1: City | D1: Phone
A2: S001 | B2: DailyDairy 1 | C2: Howrah | D2: +91-9624636385
A3: S002 | B3: BakersHub 2 | C3: Durgapur | D3: +91-9120912992
A4: S003 | B4: FreshFoods 3 | C4: Durgapur | D4: +91-9220117054
A5: S004 | B5: Tea&Co 4 | C5: Jamshedpur | D5: +91-9489747629
A6: S005 | B6: SpiceRoute 5 | C6: Durgapur | D6: +91-9992994062
A7: S006 | B7: DailyDairy 6 | C7: Howrah | D7: +91-9966267851
A8: S007 | B8: SpiceRoute 7 | C8: Howrah | D8: +91-9430190783
A9: S008 | B9: AgroDelight 8 | C9: Kolkata | D9: +91-9357109965
A10: S009 | B10: Tea&Co 9 | C10: Howrah | D10: +91-9162196678
A11: S010 | B11: SpiceRoute 10 | C11: Jamshedpur | D11: +91-9358633898

Sheet WasteLog
A1: Date | B1: SKU | C1: Qty | D1: Reason | E1: Waste cost
A2: 45867 | B2: BHL1C3 | C2: 2 | D2: Spoilage | E2: =(_xlfn.XLOOKUP(WasteLog[[#This Row],[SKU]],Menu[SKU],Menu[UnitCost]))*WasteLog[[#This Row],[Qty]] -> 18.76
A3: 45860 | B3: HH1DNM | C3: 4 | D3: Damaged | E3: =(_xlfn.XLOOKUP(WasteLog[[#This Row],[SKU]],Menu[SKU],Menu[UnitCost]))*WasteLog[[#This Row],[Qty]] -> 448.32
A4: 45853 | B4: B0T0PV | C4: 2 | D4: Expired | E4: =(_xlfn.XLOOKUP(WasteLog[[#This Row],[SKU]],Menu[SKU],Menu[UnitCost]))*WasteLog[[#This Row],[Qty]] -> 27.78
A5: 45879 | B5: D9T84A | C5: 2 | D5: Damaged | E5: =(_xlfn.XLOOKUP(WasteLog[[#This Row],[SKU]],Menu[SKU],Menu[UnitCost]))*WasteLog[[#This Row],[Qty]] -> 97.94
A6: 45891 | B6: SCKW5N | C6: 2 | D6: Spoilage | E6: =(_xlfn.XLOOKUP(WasteLog[[#This Row],[SKU]],Menu[SKU],Menu[UnitCost]))*WasteLog[[#This Row],[Qty]] -> 71.62
A7: 45896 | B7: HUZZPQ | C7: 1 | D7: Damaged | E7: =(_xlfn.XLOOKUP(WasteLog[[#This Row],[SKU]],Menu[SKU],Menu[UnitCost]))*WasteLog[[#This Row],[Qty]] -> 80.92
A8: 45890 | B8: BHL1C3 | C8: 3 | D8: Overproduction | E8: =(_xlfn.XLOOKUP(WasteLog[[#This Row],[SKU]],Menu[SKU],Menu[UnitCost]))*WasteLog[[#This Row],[Qty]] -> 28.14
A9: 45893 | B9: H3A3ZM | C9: 1 | D9: Overproduction | E9: =(_xlfn.XLOOKUP(WasteLog[[#This Row],[SKU]],Menu[SKU],Menu[UnitCost]))*WasteLog[[#This Row],[Qty]] -> 74.07
A10: 45892 | B10: DFFYVN | C10: 2 | D10: Spoilage | E10: =(_xlfn.XLOOKUP(WasteLog[[#This Row],[SKU]],Menu[SKU],Menu[UnitCost]))*WasteLog[[#This Row],[Qty]] -> 43.9
A11: 45894 | B11: D9T84A | C11: 1 | D11: Spoilage | E11: =(_xlfn.XLOOKUP(WasteLog[[#This Row],[SKU]],Menu[SKU],Menu[UnitCost]))*WasteLog[[#This Row],[Qty]] -> 48.97
A12: 45854 | B12: BTIQJ7 | C12: 1 | D12: Damaged | E12: =(_xlfn.XLOOKUP(WasteLog[[#This Row],[SKU]],Menu[SKU],Menu[UnitCost]))*WasteLog[[#This Row],[Qty]] -> 14.18
A13: 45850 | B13: SCKW5N | C13: 4 | D13: Damaged | E13: =(_xlfn.XLOOKUP(WasteLog[[#This Row],[SKU]],Menu[SKU],Menu[UnitCost]))*WasteLog[[#This Row],[Qty]] -> 143.24
... A121: 45847 | B121: SHJ7XV | C121: 2 | D121: Spoilage | E121: =(_xlfn.XLOOKUP(WasteLog[[#This Row],[SKU]],Menu[SKU],Menu[UnitCost]))*WasteLog[[#This Row],[Qty]] -> 51.6

Sheet Feedback
A1: Date | B1: Branch | C1: Rating | D1: Comment
A2: 45846 | B2: Plant 1 Canteen | C2: 4 | D2: Ok
A3: 45875 | B3: Head Office Café | C3: 3 | D3: Great staff
A4: 45869 | B4: Plant 2 Canteen | C4: 2 | D4: Good
A5: 45839 | B5: Plant 2 Canteen | C5: 5 | D5: Less spicy
A6: 45865 | B6: Plant 1 Canteen | C6: 3 | D6: Good
A7: 45857 | B7: Plant 2 Canteen | C7: 5 | D7: Great staff
A8: 45849 | B8: Plant 1 Canteen | C8: 2 | D8: Less spicy
A9: 45892 | B9: Plant 1 Canteen | C9: 4 | D9: Great staff
A10: 45840 | B10: Plant 2 Canteen | C10: 5 | D10: Great staff
A11: 45847 | B11: Head Office Café | C11: 3 | D11: Ok
A12: 45875 | B12: Plant 1 Canteen | C12: 3 | D12: Loved chai
A13: 45868 | B13: Plant 2 Canteen | C13: 5 | D13: Ok
... A17: 45896 | B17: Head Office Café | C17: 3 | D17: Crowded
A18: 45849 | B18: Plant 1 Canteen | C18: 4
A19: 45877 | B19: Plant 2 Canteen | C19: 5 | D19: Less spicy
A20: 45881 | B20: Plant 2 Canteen | C20: 5 | D20: Ok
A21: 45868 | B21: Plant 2 Canteen | C21: 3 | D21: Crowded
A22: 45869 | B22: Plant 1 Canteen | C22: 5 | D22: Less spicy
A23: 45867 | B23: Head Office Café | C23: 5 | D23: Slow service
A24: 45870 | B24: Plant 2 Canteen | C24: 4 | D24: Great staff
A25: 45874 | B25: Plant 1 Canteen | C25: 3 | D25: Ok
A26: 45892 | B26: Plant 1 Canteen | C26: 5 | D26: Slow service
A27: 45881 | B27: Plant 2 Canteen | C27: 2 | D27: Great staff
A28: 45887 | B28: Plant 1 Canteen | C28: 4 | D28: Slow service
A29: 45863 | B29: Head Office Café | C29: 3 | D29: Great staff
A30: 45875 | B30: Plant 1 Canteen | C30: 5 | D30: Crowded
A31: 45895 | B31: Plant 2 Canteen | C31: 5
A32: 45873 | B32: Head Office Café | C32: 2 | D32: Good
A33: 45863 | B33: Head Office Café | C33: 4 | D33: Ok
A34: 45843 | B34: Head Office Café | C34: 5 | D34: Less spicy
A35: 45880 | B35: Plant 1 Canteen | C35: 2 | D35: Good
A36: 45864 | B36: Plant 1 Canteen | C36: 3 | D36: Crowded
A37: 45875 | B37: Plant 2 Canteen | C37: 5 | D37: Ok
A38: 45872 | B38: Plant 1 Canteen | C38: 5 | D38: Good
A39: 45867 | B39: Plant 2 Canteen | C39: 2 | D39: Good
A40: 45852 | B40: Plant 2 Canteen | C40: 4 | D40: Less spicy
A41: 45883 | B41: Plant 1 Canteen | C41: 5 | D41: Less spicy
A42: 45885 | B42: Plant 1 Canteen | C42: 5 | D42: Crowded
A43: 45869 | B43: Plant 1 Canteen | C43: 4
A44: 45850 | B44: Plant 1 Canteen | C44: 4 | D44: Good
A45: 45854 | B45: Head Office Café | C45: 3 | D45: Ok
A46: 45892 | B46: Plant 1 Canteen | C46: 4 | D46: Great staff
A47: 45883 | B47: Plant 1 Canteen | C47: 5 | D47: Ok
A48: 45857 | B48: Head Office Café | C48: 5 | D48: Great staff
A49: 45841 | B49: Head Office Café | C49: 3 | D49: Crowded
A50: 45896 | B50: Plant 2 Canteen | C50: 5
A51: 45859 | B51: Plant 1 Canteen | C51: 4 | D51: Good
A52: 45895 | B52: Plant 1 Canteen | C52: 3 | D52: Less spicy
A53: 45870 | B53: Plant 1 Canteen | C53: 5 | D53: Good
A54: 45864 | B54: Head Office Café | C54: 5 | D54: Less spicy
A55: 45896 | B55: Plant 2 Canteen | C55: 5 | D55: Good
A56: 45872 | B56: Plant 2 Canteen | C56: 5 | D56: Ok
A57: 45867 | B57: Head Office Café | C57: 2 | D57: Ok
A58: 45869 | B58: Plant 1 Canteen | C58: 3 | D58: Loved chai
A59: 45850 | B59: Plant 1 Canteen | C59: 4 | D59: Ok
A60: 45888 | B60: Plant 2 Canteen | C60: 5 | D60: Ok
A61: 45894 | B61: Plant 2 Canteen | C61: 5 | D61: Ok
A62: 45886 | B62: Head Office Café | C62: 3 | D62: Ok
... A87: 45848 | B87: Plant 2 Canteen | C87: 4 | D87: Less spicy
A88: 45883 | B88: Plant 2 Canteen | C88: 4
A89: 45848 | B89: Head Office Café | C89: 5 | D89: Less spicy
A90: 45845 | B90: Head Office Café | C90: 5 | D90: Slow service
A91: 45880 | B91: Plant 1 Canteen | C91: 5 | D91: Loved chai
A92: 45870 | B92: Plant 2 Canteen | C92: 4 | D92: Ok
A93: 45893 | B93: Plant 2 Canteen | C93: 4
A94: 45843 | B94: Plant 1 Canteen | C94: 5
A95: 45851 | B95: Plant 1 Canteen | C95: 5 | D95: Crowded
A96: 45839 | B96: Plant 2 Canteen | C96: 3 | D96: Ok
A97: 45868 | B97: Plant 1 Canteen | C97: 4 | D97: Good
A98: 45873 | B98: Plant 2 Canteen | C98: 2 | D98: Less spicy
A99: 45855 | B99: Plant 1 Canteen | C99: 5 | D99: Loved chai
A100: 45861 | B100: Plant 2 Canteen | C100: 2 | D100: Good
A101: 45839 | B101: Plant 1 Canteen | C101: 5 | D101: Good
A102: 45851 | B102: Head Office Café | C102: 3 | D102: Crowded
A103: 45839 | B103: Plant 1 Canteen | C103: 4 | D103: Good
A104: 45880 | B104: Head Office Café | C104: 3 | D104: Crowded
A105: 45845 | B105: Plant 1 Canteen | C105: 5 | D105: Good
A106: 45848 | B106: Plant 1 Canteen | C106: 4 | D106: Less spicy
... A114: 45865 | B114: Head Office Café | C114: 2 | D114: Slow service
A115: 45892 | B115: Head Office Café | C115: 4
A116: 45868 | B116: Plant 1 Canteen | C116: 3 | D116: Great staff
A117: 45867 | B117: Head Office Café | C117: 2 | D117: Slow service
A118: 45887 | B118: Plant 2 Canteen | C118: 2 | D118: Slow service
A119: 45887 | B119: Head Office Café | C119: 2
A120: 45874 | B120: Plant 2 Canteen | C120: 3 | D120: Great staff
A121: 45894 | B121: Plant 2 Canteen | C121: 4 | D121: Ok
A122: 45884 | B122: Plant 1 Canteen | C122: 2 | D122: Good
A123: 45840 | B123: Plant 2 Canteen | C123: 3
A124: 45844 | B124: Plant 2 Canteen | C124: 4 | D124: Great staff
A125: 45880 | B125: Head Office Café | C125: 5 | D125: Good
A126: 45891 | B126: Head Office Café | C126: 3 | D126: Loved chai
A127: 45847 | B127: Plant 2 Canteen | C127: 2 | D127: Slow service
A128: 45854 | B128: Head Office Café | C128: 4 | D128: Great staff
A129: 45895 | B129: Head Office Café | C129: 2 | D129: Loved chai
A130: 45881 | B130: Head Office Café | C130: 3
A131: 45862 | B131: Plant 1 Canteen | C131: 5 | D131: Good
A132: 45883 | B132: Head Office Café | C132: 2 | D132: Loved chai
A133: 45856 | B133: Plant 1 Canteen | C133: 2 | D133: Ok
A134: 45840 | B134: Plant 1 Canteen | C134: 5 | D134: Less spicy
...
